// converted by version 1.3
// on Sat Jan 03 12:20:25 ICT 2026

.package HospitalCard {
	.aid 0x11:0x22:0x33:0x44:0x55;
	.version 1.0;

	.imports {
		0xA0:0x0:0x0:0x0:0x62:0x0:0x1 1.0;		//java/lang
		0xA0:0x0:0x0:0x0:0x62:0x1:0x2 1.2;		//javacard/security
		0xA0:0x0:0x0:0x0:0x62:0x1:0x1 1.2;		//javacard/framework
		0xA0:0x0:0x0:0x0:0x62:0x2:0x1 1.2;		//javacardx/crypto
	}

	.applet {
		0x11:0x22:0x33:0x44:0x55:0x1 UserApplet;
	}

	.constantPool {
		// 0
		instanceFieldRef byte[] UserApplet/cardID;
		// 1
		instanceFieldRef byte[] UserApplet/hashPinUser;
		// 2
		instanceFieldRef byte[] UserApplet/hashPinAdminReset;
		// 3
		instanceFieldRef byte[] UserApplet/encUser;
		// 4
		instanceFieldRef byte[] UserApplet/encAdmin;
		// 5
		instanceFieldRef byte[] UserApplet/encPatient;
		// 6
		instanceFieldRef byte[] UserApplet/encPhoto;
		// 7
		instanceFieldRef byte[] UserApplet/encBalance;
		// 8
		instanceFieldRef byte[] UserApplet/lastTxnHash;
		// 9
		instanceFieldRef byte[] UserApplet/mkUser;
		// 10
		instanceFieldRef byte[] UserApplet/tempHashBuffer;
		// 11
		instanceFieldRef byte[] UserApplet/tempPinBuffer;
		// 12
		instanceFieldRef byte[] UserApplet/tempDecryptBuffer;
		// 13
		instanceFieldRef byte[] UserApplet/tempBalanceBuffer;
		// 14
		instanceFieldRef byte UserApplet/initialized;
		// 15
		instanceFieldRef byte UserApplet/pinRetryCounter;
		// 16
		instanceFieldRef byte UserApplet/blockedFlag;
		// 17
		instanceFieldRef byte UserApplet/pinChangedFlag;
		// 18
		instanceFieldRef short UserApplet/encPatientLength;
		// 19
		instanceFieldRef short UserApplet/encPhotoLength;
		// 20
		instanceFieldRef short UserApplet/txnCounter;
		// 21
		instanceFieldRef 1.11 UserApplet/sha256;
		// 22
		instanceFieldRef 3.1 UserApplet/aesCipher;
		// 23
		instanceFieldRef 1.20 UserApplet/aesKey;
		// 24
		instanceFieldRef 1.14 UserApplet/randomData;
		// 25
		instanceFieldRef 1.16 UserApplet/rsaKeyPair;
		// 26
		instanceFieldRef 3.1 UserApplet/rsaCipher;
		// 27
		instanceFieldRef 1.8 UserApplet/skUser;
		// 28
		instanceFieldRef 1.9 UserApplet/pkUser;
		// 29
		staticMethodRef 1.11.0(BZ)Ljavacard/security/MessageDigest;;		// javacard/security/MessageDigest.getInstance(BZ)Ljavacard/security/MessageDigest;
			.descriptor	Ljavacard/security/MessageDigest;	1.11;

		// 30
		virtualMethodRef 1.11.4()V;		// javacard/security/MessageDigest.reset()V
		// 31
		virtualMethodRef 1.11.5([BSS)V;		// javacard/security/MessageDigest.update([BSS)V
		// 32
		virtualMethodRef 1.11.1([BSS[BS)S;		// javacard/security/MessageDigest.doFinal([BSS[BS)S
		// 33
		staticMethodRef 2.16.3([BSSB)S;		// javacard/framework/Util.arrayFillNonAtomic([BSSB)S
		// 34
		staticMethodRef 2.16.2([BS[BSS)S;		// javacard/framework/Util.arrayCopyNonAtomic([BS[BSS)S
		// 35
		staticMethodRef CryptoHelper/KDF([BSS[BSSS[BSLjavacard/security/MessageDigest;[BS)V;
			.descriptor	Ljavacard/security/MessageDigest;	1.11;

		// 36
		classRef 0.2;		// java/lang/Exception
		// 37
		classRef 1.20;		// javacard/security/AESKey
		// 38
		virtualMethodRef 3.1.3(Ljavacard/security/Key;B)V;		// javacardx/crypto/Cipher.init(Ljavacard/security/Key;B)V
			.descriptor	Ljavacard/security/Key;	1.0;

		// 39
		staticMethodRef 2.8.13(SB)[B;		// javacard/framework/JCSystem.makeTransientByteArray(SB)[B
		// 40
		virtualMethodRef 3.1.1([BSS[BS)S;		// javacardx/crypto/Cipher.doFinal([BSS[BS)S
		// 41
		staticMethodRef CryptoHelper/deriveKeyFromPin([BSS[B[B)V;
		// 42
		classRef 1.12;		// javacard/security/CryptoException
		// 43
		virtualMethodRef 1.12.1()S;		// javacard/security/CryptoException.getReason()S
		// 44
		staticMethodRef 2.7.1(S)V;		// javacard/framework/ISOException.throwIt(S)V
		// 45
		staticMethodRef 2.16.4([BS)S;		// javacard/framework/Util.getShort([BS)S
		// 46
		staticMethodRef 2.16.1([BS[BSS)S;		// javacard/framework/Util.arrayCopy([BS[BSS)S
		// 47
		staticMethodRef DataHelper/setInt([BSI)V;
		// 48
		staticMethodRef 2.16.6([BSS)S;		// javacard/framework/Util.setShort([BSS)S
		// 49
		staticMethodRef CryptoHelper/hashPin([BSS[B[B)S;
		// 50
		staticMethodRef 3.1.0(BZ)Ljavacardx/crypto/Cipher;;		// javacardx/crypto/Cipher.getInstance(BZ)Ljavacardx/crypto/Cipher;
			.descriptor	Ljavacardx/crypto/Cipher;	3.1;

		// 51
		staticMethodRef 2.16.0([BS[BSS)B;		// javacard/framework/Util.arrayCompare([BS[BSS)B
		// 52
		staticMethodRef 1.13.0(BSZ)Ljavacard/security/Key;;		// javacard/security/KeyBuilder.buildKey(BSZ)Ljavacard/security/Key;
			.descriptor	Ljavacard/security/Key;	1.0;

		// 53
		classRef 1.8;		// javacard/security/RSAPrivateKey
		// 54
		staticMethodRef 1.14.0(B)Ljavacard/security/RandomData;;		// javacard/security/RandomData.getInstance(B)Ljavacard/security/RandomData;
			.descriptor	Ljavacard/security/RandomData;	1.14;

		// 55
		classRef 1.9;		// javacard/security/RSAPublicKey
		// 56
		classRef 1.16;		// javacard/security/KeyPair
		// 57
		staticMethodRef 1.16.0(BS)V;		// javacard/security/KeyPair.<init>(BS)V
		// 58
		virtualMethodRef 1.16.2()Ljavacard/security/PrivateKey;;		// javacard/security/KeyPair.getPrivate()Ljavacard/security/PrivateKey;
			.descriptor	Ljavacard/security/PrivateKey;	1.2;

		// 59
		virtualMethodRef 1.16.1()V;		// javacard/security/KeyPair.genKeyPair()V
		// 60
		virtualMethodRef 2.3.2([BSB)V;		// javacard/framework/Applet.register([BSB)V
		// 61
		classRef UserApplet;
		// 62
		staticMethodRef UserApplet/<init>([BSB)V;
		// 63
		virtualMethodRef 2.3.3()Z;		// javacard/framework/Applet.selectingApplet()Z
		// 64
		virtualMethodRef 2.10.1()[B;		// javacard/framework/APDU.getBuffer()[B
		// 65
		virtualMethodRef 2.10.6()S;		// javacard/framework/APDU.setIncomingAndReceive()S
		// 66
		staticMethodRef UserApplet/getStatus(Ljavacard/framework/APDU;)V;
			.descriptor	Ljavacard/framework/APDU;	2.10;

		// 67
		staticMethodRef UserApplet/issueCard(Ljavacard/framework/APDU;)V;
			.descriptor	Ljavacard/framework/APDU;	2.10;

		// 68
		staticMethodRef UserApplet/verifyPinAndReadData(Ljavacard/framework/APDU;)V;
			.descriptor	Ljavacard/framework/APDU;	2.10;

		// 69
		staticMethodRef UserApplet/updatePatientData(Ljavacard/framework/APDU;)V;
			.descriptor	Ljavacard/framework/APDU;	2.10;

		// 70
		staticMethodRef UserApplet/adminResetPin(Ljavacard/framework/APDU;)V;
			.descriptor	Ljavacard/framework/APDU;	2.10;

		// 71
		staticMethodRef UserApplet/changePin(Ljavacard/framework/APDU;)V;
			.descriptor	Ljavacard/framework/APDU;	2.10;

		// 72
		staticMethodRef UserApplet/debitTransaction(Ljavacard/framework/APDU;)V;
			.descriptor	Ljavacard/framework/APDU;	2.10;

		// 73
		staticMethodRef UserApplet/getTxnStatus(Ljavacard/framework/APDU;)V;
			.descriptor	Ljavacard/framework/APDU;	2.10;

		// 74
		staticMethodRef UserApplet/creditTransaction(Ljavacard/framework/APDU;)V;
			.descriptor	Ljavacard/framework/APDU;	2.10;

		// 75
		staticMethodRef UserApplet/signChallenge(Ljavacard/framework/APDU;)V;
			.descriptor	Ljavacard/framework/APDU;	2.10;

		// 76
		staticMethodRef UserApplet/getPinChangeStatus(Ljavacard/framework/APDU;)V;
			.descriptor	Ljavacard/framework/APDU;	2.10;

		// 77
		staticMethodRef UserApplet/setPhoto(Ljavacard/framework/APDU;)V;
			.descriptor	Ljavacard/framework/APDU;	2.10;

		// 78
		staticMethodRef UserApplet/getPhoto(Ljavacard/framework/APDU;)V;
			.descriptor	Ljavacard/framework/APDU;	2.10;

		// 79
		virtualMethodRef 2.10.8(SS)V;		// javacard/framework/APDU.setOutgoingAndSend(SS)V
		// 80
		classRef 0.5;		// java/lang/ArrayIndexOutOfBoundsException
		// 81
		staticMethodRef 2.8.15(SB)[S;		// javacard/framework/JCSystem.makeTransientShortArray(SB)[S
		// 82
		staticMethodRef UserApplet/parseIssueCardInput([B[S)V;
		// 83
		staticMethodRef UserApplet/generateAndInitializeKeys()V;
		// 84
		staticMethodRef UserApplet/setupPINsAndEncryptMK([BSS)V;
		// 85
		staticMethodRef UserApplet/encryptAndStorePatientData([BSS)V;
		// 86
		staticMethodRef UserApplet/encryptAndStoreBalance(I)V;
		// 87
		staticMethodRef UserApplet/buildIssueCardResponse([B)S;
		// 88
		classRef 2.7;		// javacard/framework/ISOException
		// 89
		classRef 0.7;		// java/lang/NullPointerException
		// 90
		staticMethodRef UserApplet/validateAndVerifyPIN([BSS)V;
		// 91
		staticMethodRef UserApplet/decryptDataAndBuildResponse([BSSLjavacard/framework/APDU;)S;
			.descriptor	Ljavacard/framework/APDU;	2.10;

		// 92
		virtualMethodRef 2.7.1()S;		// javacard/framework/ISOException.getReason()S
		// 93
		staticMethodRef UserApplet/isMasterKeyValid()Z;
		// 94
		staticMethodRef UserApplet/validatePINChange([BSSSS[B)V;
		// 95
		staticMethodRef UserApplet/reEncryptMasterKeyWithNewPIN([BSSSS[B)V;
		// 96
		staticMethodRef PINHelper/safeHash(Ljavacard/security/MessageDigest;[BSS[BS)V;
			.descriptor	Ljavacard/security/MessageDigest;	1.11;

		// 97
		staticMethodRef CryptoHelper/unwrapMasterKeyWithPIN([BSS[BSSS[B[BLjavacardx/crypto/Cipher;Ljavacard/security/AESKey;Ljavacard/security/MessageDigest;[BS)Z;
			.descriptor	Ljavacardx/crypto/Cipher;	3.1;
			.descriptor	Ljavacard/security/AESKey;	1.20;
			.descriptor	Ljavacard/security/MessageDigest;	1.11;

		// 98
		staticMethodRef RSAHelper/generateKeyPair(Ljavacard/security/KeyPair;)Z;
			.descriptor	Ljavacard/security/KeyPair;	1.16;

		// 99
		staticMethodRef 2.3.0()V;		// javacard/framework/Applet.<init>()V
		// 100
		virtualMethodRef 1.16.3()Ljavacard/security/PublicKey;;		// javacard/security/KeyPair.getPublic()Ljavacard/security/PublicKey;
			.descriptor	Ljavacard/security/PublicKey;	1.3;

		// 101
		staticMethodRef 0.0.0()V;		// java/lang/Object.<init>()V
		// 102
		staticMethodRef CryptoHelper/wrapMasterKeyWithPIN([BSS[BSSS[B[BLjavacardx/crypto/Cipher;Ljavacard/security/AESKey;Ljavacard/security/MessageDigest;[BS)V;
			.descriptor	Ljavacardx/crypto/Cipher;	3.1;
			.descriptor	Ljavacard/security/AESKey;	1.20;
			.descriptor	Ljavacard/security/MessageDigest;	1.11;

		// 103
		staticMethodRef RSAHelper/getPublicKeyBytes(Ljavacard/security/RSAPublicKey;[BS)S;
			.descriptor	Ljavacard/security/RSAPublicKey;	1.9;

		// 104
		staticMethodRef RSAHelper/sign(Ljavacardx/crypto/Cipher;Ljavacard/security/RSAPrivateKey;[BSS[BS)S;
			.descriptor	Ljavacardx/crypto/Cipher;	3.1;
			.descriptor	Ljavacard/security/RSAPrivateKey;	1.8;

		// 105
		staticMethodRef DataHelper/getInt([BS)I;
		// 106
		staticMethodRef UserApplet/processTransaction(Ljavacard/framework/APDU;Z)V;
			.descriptor	Ljavacard/framework/APDU;	2.10;

		// 107
		virtualMethodRef 1.14.1([BSS)V;		// javacard/security/RandomData.generateData([BSS)V
	}

	.class public CryptoHelper 0 extends 0.0 {		// extends java/lang/Object

		.publicMethodTable 1 {
			equals(Ljava/lang/Object;)Z;
		}

		.packageMethodTable 0 {
		}

		.method public <init>()V 0 {
			.stack 1;
			.locals 0;

				L0:	aload_0;
					invokespecial 101;		// java/lang/Object.<init>()V
					return;
		}

		.method public static hashPin([BSS[B[B)S 1 {
			.stack 6;
			.locals 1;

				L0:	sconst_1;
					sconst_0;
					invokestatic 29;		// javacard/security/MessageDigest.getInstance(BZ)Ljavacard/security/MessageDigest;
					astore 5;
				L1:	aload 5;
					invokevirtual 30;		// javacard/security/MessageDigest.reset()V
					aload 5;
					aload_0;
					sload_1;
					sload_2;
					invokevirtual 31;		// javacard/security/MessageDigest.update([BSS)V
					aload 5;
					aload_3;
					sconst_0;
					bspush 16;
					aload 4;
					sconst_0;
					invokevirtual 32;		// javacard/security/MessageDigest.doFinal([BSS[BS)S
					pop;
					bspush 20;
					sreturn;
		}

		.method public static deriveKeyFromPin([BSS[B[B)V 2 {
			.stack 6;
			.locals 1;

				L0:	sconst_1;
					sconst_0;
					invokestatic 29;		// javacard/security/MessageDigest.getInstance(BZ)Ljavacard/security/MessageDigest;
					astore 5;
				L1:	aload 5;
					invokevirtual 30;		// javacard/security/MessageDigest.reset()V
					aload 5;
					aload_0;
					sload_1;
					sload_2;
					invokevirtual 31;		// javacard/security/MessageDigest.update([BSS)V
					aload 5;
					aload_3;
					sconst_0;
					bspush 16;
					aload 4;
					sconst_0;
					invokevirtual 32;		// javacard/security/MessageDigest.doFinal([BSS[BS)S
					pop;
					return;
		}

		.method public static KDF([BSS[BSSS[BSLjavacard/security/MessageDigest;[BS)V 3 {
			.stack 6;
			.locals 6;

			.descriptor	Ljavacard/security/MessageDigest;	1.11;

				L0:	sload 6;
					sconst_1;
					if_scmpge L2;
				L1:	sconst_1;
					sstore 6;
				L2:	sload 6;
					s2i;
					iipush 65535;
					icmp;
					ifle L4;
				L3:	sconst_m1;
					sstore 6;
				L4:	sload 11;
					sstore 12;
				L5:	sload 11;
					bspush 20;
					sadd;
					sstore 13;
				L6:	sload 11;
					bspush 40;
					sadd;
					sstore 14;
				L7:	aload 7;
					sload 8;
					bspush 20;
					sconst_0;
					invokestatic 33;		// javacard/framework/Util.arrayFillNonAtomic([BSSB)S
					pop;
					sload 14;
					sstore 15;
				L8:	aload_0;
					sload_1;
					aload 10;
					sload 15;
					sload_2;
					invokestatic 34;		// javacard/framework/Util.arrayCopyNonAtomic([BS[BSS)S
					pop;
					sload 15;
					sload_2;
					sadd;
					sstore 15;
					aload_3;
					sload 4;
					aload 10;
					sload 15;
					sload 5;
					invokestatic 34;		// javacard/framework/Util.arrayCopyNonAtomic([BS[BSS)S
					pop;
					sload 15;
					sload 5;
					sadd;
					sstore 15;
					aload 10;
					sload 15;
					sinc 15 1;
					sconst_0;
					bastore;
					aload 10;
					sload 15;
					sinc 15 1;
					sconst_0;
					bastore;
					aload 10;
					sload 15;
					sinc 15 1;
					sconst_0;
					bastore;
					aload 10;
					sload 15;
					sinc 15 1;
					sconst_1;
					bastore;
					aload 9;
					invokevirtual 30;		// javacard/security/MessageDigest.reset()V
					aload 9;
					aload 10;
					sload 14;
					sload 15;
					sload 14;
					ssub;
					aload 10;
					sload 12;
					invokevirtual 32;		// javacard/security/MessageDigest.doFinal([BSS[BS)S
					pop;
					sconst_0;
					sstore 16;
				L9:	sload 16;
					bspush 20;
					if_scmpge L11;
				L10:	aload 7;
					sload 8;
					sload 16;
					sadd;
					aload 7;
					sload 8;
					sload 16;
					sadd;
					baload;
					aload 10;
					sload 12;
					sload 16;
					sadd;
					baload;
					sxor;
					bastore;
					sinc 16 1;
					goto L9;
				L11:	aload 10;
					sload 12;
					aload 10;
					sload 13;
					bspush 20;
					invokestatic 34;		// javacard/framework/Util.arrayCopyNonAtomic([BS[BSS)S
					pop;
					sconst_2;
					sstore 16;
				L12:	sload 16;
					sload 6;
					if_scmpgt L17;
				L13:	sload 14;
					sstore 15;
					aload_0;
					sload_1;
					aload 10;
					sload 15;
					sload_2;
					invokestatic 34;		// javacard/framework/Util.arrayCopyNonAtomic([BS[BSS)S
					pop;
					sload 15;
					sload_2;
					sadd;
					sstore 15;
					aload 10;
					sload 13;
					aload 10;
					sload 15;
					bspush 20;
					invokestatic 34;		// javacard/framework/Util.arrayCopyNonAtomic([BS[BSS)S
					pop;
					sinc 15 20;
					aload 9;
					invokevirtual 30;		// javacard/security/MessageDigest.reset()V
					aload 9;
					aload 10;
					sload 14;
					sload 15;
					sload 14;
					ssub;
					aload 10;
					sload 12;
					invokevirtual 32;		// javacard/security/MessageDigest.doFinal([BSS[BS)S
					pop;
					sconst_0;
					sstore 17;
				L14:	sload 17;
					bspush 20;
					if_scmpge L16;
				L15:	aload 7;
					sload 8;
					sload 17;
					sadd;
					aload 7;
					sload 8;
					sload 17;
					sadd;
					baload;
					aload 10;
					sload 12;
					sload 17;
					sadd;
					baload;
					sxor;
					bastore;
					sinc 17 1;
					goto L14;
				L16:	aload 10;
					sload 12;
					aload 10;
					sload 13;
					bspush 20;
					invokestatic 34;		// javacard/framework/Util.arrayCopyNonAtomic([BS[BSS)S
					pop;
					sinc 16 1;
					goto L12;
				L17:	return;
		}

		.method public static KDF([BSS[BS[BLjavacard/security/MessageDigest;[BS)V 4 {
			.stack 12;
			.locals 0;

			.descriptor	Ljavacard/security/MessageDigest;	1.11;

				L0:	aload_0;
					sload_1;
					sload_2;
					aload_3;
					sconst_0;
					bspush 16;
					sload 4;
					aload 5;
					sconst_0;
					aload 6;
					aload 7;
					sload 8;
					invokestatic 35;		// HospitalCard/CryptoHelper.KDF([BSS[BSSS[BSLjavacard/security/MessageDigest;[BS)V
					return;
		}

		.method public static encryptAES([B[BSS[BLjavacardx/crypto/Cipher;Ljavacard/security/AESKey;)S 5 {
			.stack 6;
			.locals 4;

			.descriptor	Ljavacardx/crypto/Cipher;	3.1;
			.descriptor	Ljavacard/security/AESKey;	1.20;

				L0:	aload 6;
					aload_0;
					sconst_0;
					invokeinterface 3 37 4;		// javacard/security/AESKey
					aload 5;
					aload 6;
					sconst_2;
					invokevirtual 38;		// javacardx/crypto/Cipher.init(Ljavacard/security/Key;B)V
					bspush 16;
					sload_3;
					bspush 16;
					srem;
					ssub;
					sstore 7;
				L1:	sload 7;
					ifne L3;
				L2:	bspush 16;
					sstore 7;
				L3:	sload_3;
					sload 7;
					sadd;
					sstore 8;
				L4:	sload 8;
					sconst_2;
					invokestatic 39;		// javacard/framework/JCSystem.makeTransientByteArray(SB)[B
					astore 9;
				L5:	aload_1;
					sload_2;
					aload 9;
					sconst_0;
					sload_3;
					invokestatic 34;		// javacard/framework/Util.arrayCopyNonAtomic([BS[BSS)S
					pop;
					sload_3;
					sstore 10;
				L6:	sload 10;
					sload 8;
					if_scmpge L8;
				L7:	aload 9;
					sload 10;
					sload 7;
					s2b;
					bastore;
					sinc 10 1;
					goto L6;
				L8:	aload 5;
					aload 9;
					sconst_0;
					sload 8;
					aload 4;
					sconst_0;
					invokevirtual 40;		// javacardx/crypto/Cipher.doFinal([BSS[BS)S
				L9:	sreturn;
				L10:	astore 9;
				L11:	sconst_0;
					sreturn;
			.exceptionTable {
				// start_block end_block handler_block catch_type_index
				L4 L9 L10 36;
			}
		}

		.method public static decryptAES([B[BSS[BLjavacardx/crypto/Cipher;Ljavacard/security/AESKey;)S 6 {
			.stack 6;
			.locals 2;

			.descriptor	Ljavacardx/crypto/Cipher;	3.1;
			.descriptor	Ljavacard/security/AESKey;	1.20;

				L0:	aload 6;
					aload_0;
					sconst_0;
					invokeinterface 3 37 4;		// javacard/security/AESKey
					aload 5;
					aload 6;
					sconst_1;
					invokevirtual 38;		// javacardx/crypto/Cipher.init(Ljavacard/security/Key;B)V
				L1:	aload 5;
					aload_1;
					sload_2;
					sload_3;
					aload 4;
					sconst_0;
					invokevirtual 40;		// javacardx/crypto/Cipher.doFinal([BSS[BS)S
					sstore 7;
				L2:	sload 7;
					ifle L7;
				L3:	aload 4;
					sload 7;
					sconst_1;
					ssub;
					baload;
					sstore 8;
				L4:	sload 8;
					sconst_1;
					if_scmplt L7;
				L5:	sload 8;
					bspush 16;
					if_scmpgt L7;
				L6:	sload 7;
					sload 8;
					ssub;
					sstore 7;
				L7:	sload 7;
				L8:	sreturn;
				L9:	astore 7;
				L10:	sconst_0;
					sreturn;
			.exceptionTable {
				// start_block end_block handler_block catch_type_index
				L1 L8 L9 36;
			}
		}

		.method public static decryptMasterKeyWithPin([BSS[B[B[BLjavacardx/crypto/Cipher;Ljavacard/security/AESKey;Ljavacard/security/MessageDigest;)V 7 {
			.stack 6;
			.locals 1;

			.descriptor	Ljavacardx/crypto/Cipher;	3.1;
			.descriptor	Ljavacard/security/AESKey;	1.20;
			.descriptor	Ljavacard/security/MessageDigest;	1.11;

				L0:	aload_0;
					sload_1;
					sload_2;
					aload_3;
					aload 5;
					invokestatic 41;		// HospitalCard/CryptoHelper.deriveKeyFromPin([BSS[B[B)V
				L1:	aload 7;
					aload 5;
					sconst_0;
					invokeinterface 3 37 4;		// javacard/security/AESKey
					aload 6;
					aload 7;
					sconst_1;
					invokevirtual 38;		// javacardx/crypto/Cipher.init(Ljavacard/security/Key;B)V
					aload 6;
					aload 4;
					sconst_0;
					bspush 16;
					aload 5;
					sconst_0;
					invokevirtual 40;		// javacardx/crypto/Cipher.doFinal([BSS[BS)S
					pop;
					aload 7;
					aload 5;
					sconst_0;
					invokeinterface 3 37 4;		// javacard/security/AESKey
				L2:	goto L4;
				L3:	astore 9;
				L4:	return;
			.exceptionTable {
				// start_block end_block handler_block catch_type_index
				L1 L2 L3 36;
			}
		}

		.method public static encryptMasterKey([BSS[B[B[BLjavacardx/crypto/Cipher;Ljavacard/security/AESKey;)V 8 {
			.stack 6;
			.locals 0;

			.descriptor	Ljavacardx/crypto/Cipher;	3.1;
			.descriptor	Ljavacard/security/AESKey;	1.20;

				L0:	aload_0;
					sload_1;
					sload_2;
					aload_3;
					aload 5;
					invokestatic 41;		// HospitalCard/CryptoHelper.deriveKeyFromPin([BSS[B[B)V
					aload 7;
					aload 5;
					sconst_0;
					invokeinterface 3 37 4;		// javacard/security/AESKey
					aload 6;
					aload 7;
					sconst_2;
					invokevirtual 38;		// javacardx/crypto/Cipher.init(Ljavacard/security/Key;B)V
					aload 6;
					aload 4;
					sconst_0;
					bspush 16;
					aload 5;
					sconst_0;
					invokevirtual 40;		// javacardx/crypto/Cipher.doFinal([BSS[BS)S
					pop;
					return;
		}

		.method public static wrapMasterKeyWithPIN([BSS[BSSS[B[BLjavacardx/crypto/Cipher;Ljavacard/security/AESKey;Ljavacard/security/MessageDigest;[BS)V 9 {
			.stack 12;
			.locals 4;

			.descriptor	Ljavacardx/crypto/Cipher;	3.1;
			.descriptor	Ljavacard/security/AESKey;	1.20;
			.descriptor	Ljavacard/security/MessageDigest;	1.11;

				L0:	sload 13;
					sstore 14;
				L1:	sload 13;
					bspush 20;
					sadd;
					sstore 15;
				L2:	aload_0;
					sload_1;
					sload_2;
					aload_3;
					sload 4;
					sload 5;
					sload 6;
					aload 12;
					sload 14;
					aload 11;
					aload 12;
					sload 15;
					invokestatic 35;		// HospitalCard/CryptoHelper.KDF([BSS[BSSS[BSLjavacard/security/MessageDigest;[BS)V
					aload 10;
					aload 12;
					sload 14;
					invokeinterface 3 37 4;		// javacard/security/AESKey
					aload 9;
					aload 10;
					sconst_2;
					invokevirtual 38;		// javacardx/crypto/Cipher.init(Ljavacard/security/Key;B)V
					aload 9;
					aload 7;
					sconst_0;
					bspush 16;
					aload 8;
					sconst_0;
					invokevirtual 40;		// javacardx/crypto/Cipher.doFinal([BSS[BS)S
					pop;
				L3:	aload 12;
					sload 14;
					bspush 20;
					sconst_0;
					invokestatic 33;		// javacard/framework/Util.arrayFillNonAtomic([BSSB)S
					pop;
					goto L9;
				L4:	astore 16;
				L5:	sspush 28420;
					aload 16;
					invokevirtual 43;		// javacard/security/CryptoException.getReason()S
					bspush 15;
					sand;
					sor;
					invokestatic 44;		// javacard/framework/ISOException.throwIt(S)V
				L6:	aload 12;
					sload 14;
					bspush 20;
					sconst_0;
					invokestatic 33;		// javacard/framework/Util.arrayFillNonAtomic([BSSB)S
					pop;
					goto L9;
				L7:	astore 17;
				L8:	aload 12;
					sload 14;
					bspush 20;
					sconst_0;
					invokestatic 33;		// javacard/framework/Util.arrayFillNonAtomic([BSSB)S
					pop;
					aload 17;
					athrow;
				L9:	return;
			.exceptionTable {
				// start_block end_block handler_block catch_type_index
				L2 L3 L4 42;
				L2 L3 L7 0;
				L4 L6 L7 0;
				L7 L8 L7 0;
			}
		}

		.method public static unwrapMasterKeyWithPIN([BSS[BSSS[B[BLjavacardx/crypto/Cipher;Ljavacard/security/AESKey;Ljavacard/security/MessageDigest;[BS)Z 10 {
			.stack 12;
			.locals 6;

			.descriptor	Ljavacardx/crypto/Cipher;	3.1;
			.descriptor	Ljavacard/security/AESKey;	1.20;
			.descriptor	Ljavacard/security/MessageDigest;	1.11;

				L0:	sload 13;
					sstore 14;
				L1:	sload 13;
					bspush 20;
					sadd;
					sstore 15;
				L2:	aload_0;
					sload_1;
					sload_2;
					aload_3;
					sload 4;
					sload 5;
					sload 6;
					aload 12;
					sload 14;
					aload 11;
					aload 12;
					sload 15;
					invokestatic 35;		// HospitalCard/CryptoHelper.KDF([BSS[BSSS[BSLjavacard/security/MessageDigest;[BS)V
					aload 10;
					aload 12;
					sload 14;
					invokeinterface 3 37 4;		// javacard/security/AESKey
					aload 9;
					aload 10;
					sconst_1;
					invokevirtual 38;		// javacardx/crypto/Cipher.init(Ljavacard/security/Key;B)V
					aload 9;
					aload 7;
					sconst_0;
					bspush 16;
					aload 8;
					sconst_0;
					invokevirtual 40;		// javacardx/crypto/Cipher.doFinal([BSS[BS)S
					pop;
					sconst_1;
					sstore 17;
				L3:	aload 12;
					sload 14;
					bspush 20;
					sconst_0;
					invokestatic 33;		// javacard/framework/Util.arrayFillNonAtomic([BSSB)S
					pop;
					sload 17;
					sreturn;
				L4:	astore 16;
				L5:	sconst_0;
					sstore 18;
				L6:	aload 12;
					sload 14;
					bspush 20;
					sconst_0;
					invokestatic 33;		// javacard/framework/Util.arrayFillNonAtomic([BSSB)S
					pop;
					sload 18;
					sreturn;
				L7:	astore 19;
				L8:	aload 12;
					sload 14;
					bspush 20;
					sconst_0;
					invokestatic 33;		// javacard/framework/Util.arrayFillNonAtomic([BSSB)S
					pop;
					aload 19;
					athrow;
			.exceptionTable {
				// start_block end_block handler_block catch_type_index
				L2 L3 L4 42;
				L2 L3 L7 0;
				L4 L6 L7 0;
				L7 L8 L7 0;
			}
		}

	}

	.class public DataHelper 1 extends 0.0 {		// extends java/lang/Object

		.publicMethodTable 1 {
			equals(Ljava/lang/Object;)Z;
		}

		.packageMethodTable 0 {
		}

		.method public <init>()V 0 {
			.stack 1;
			.locals 0;

				L0:	aload_0;
					invokespecial 101;		// java/lang/Object.<init>()V
					return;
		}

		.method public static getInt([BS)I 1 {
			.stack 6;
			.locals 0;

				L0:	aload_0;
					sload_1;
					baload;
					s2i;
					sipush 255;
					iand;
					bipush 24;
					ishl;
					aload_0;
					sload_1;
					sconst_1;
					sadd;
					baload;
					s2i;
					sipush 255;
					iand;
					bipush 16;
					ishl;
					ior;
					aload_0;
					sload_1;
					sconst_2;
					sadd;
					baload;
					s2i;
					sipush 255;
					iand;
					bipush 8;
					ishl;
					ior;
					aload_0;
					sload_1;
					sconst_3;
					sadd;
					baload;
					s2i;
					sipush 255;
					iand;
					ior;
					ireturn;
		}

		.method public static setInt([BSI)V 2 {
			.stack 6;
			.locals 0;

				L0:	aload_0;
					sload_1;
					iload_2;
					bipush 24;
					ishr;
					i2b;
					bastore;
					aload_0;
					sload_1;
					sconst_1;
					sadd;
					iload_2;
					bipush 16;
					ishr;
					i2b;
					bastore;
					aload_0;
					sload_1;
					sconst_2;
					sadd;
					iload_2;
					bipush 8;
					ishr;
					i2b;
					bastore;
					aload_0;
					sload_1;
					sconst_3;
					sadd;
					iload_2;
					i2b;
					bastore;
					return;
		}

		.method public static parseDataWithLength([BS[B)S 3 {
			.stack 5;
			.locals 1;

				L0:	aload_0;
					sload_1;
					invokestatic 45;		// javacard/framework/Util.getShort([BS)S
					sstore_3;
				L1:	sinc 1 2;
					aload_0;
					sload_1;
					aload_2;
					sconst_0;
					sload_3;
					invokestatic 46;		// javacard/framework/Util.arrayCopy([BS[BSS)S
					pop;
					sload_1;
					sload_3;
					sadd;
					sreturn;
		}

		.method public static parsePin([BS[B)S 4 {
			.stack 5;
			.locals 1;

				L0:	aload_0;
					sload_1;
					invokestatic 45;		// javacard/framework/Util.getShort([BS)S
					sstore_3;
				L1:	sinc 1 2;
					sload_3;
					aload_2;
					arraylength;
					if_scmple L3;
				L2:	sspush 26368;
					invokestatic 44;		// javacard/framework/ISOException.throwIt(S)V
				L3:	aload_0;
					sload_1;
					aload_2;
					sconst_0;
					sload_3;
					invokestatic 46;		// javacard/framework/Util.arrayCopy([BS[BSS)S
					pop;
					sload_1;
					sreturn;
		}

		.method public static updateLogs([BSBIIS[BLjavacardx/crypto/Cipher;Ljavacard/security/AESKey;)S 5 {
			.stack 6;
			.locals 11;

			.descriptor	Ljavacardx/crypto/Cipher;	3.1;
			.descriptor	Ljavacard/security/AESKey;	1.20;

				L0:	bspush 10;
					sstore 11;
				L1:	bspush 11;
					sstore 12;
				L2:	bspush 110;
					sstore 13;
				L3:	bspush 110;
					sconst_2;
					invokestatic 39;		// javacard/framework/JCSystem.makeTransientByteArray(SB)[B
					astore 14;
				L4:	sconst_0;
					sstore 15;
				L5:	sload_1;
					ifle L10;
				L6:	aload 10;
					aload 8;
					sconst_0;
					invokeinterface 3 37 4;		// javacard/security/AESKey
					aload 9;
					aload 10;
					sconst_1;
					invokevirtual 38;		// javacardx/crypto/Cipher.init(Ljavacard/security/Key;B)V
					aload 9;
					aload_0;
					sconst_0;
					sload_1;
					aload 14;
					sconst_0;
					invokevirtual 40;		// javacardx/crypto/Cipher.doFinal([BSS[BS)S
					sstore 15;
				L7:	sload 15;
					ifle L10;
				L8:	aload 14;
					sload 15;
					sconst_1;
					ssub;
					baload;
					ifne L10;
				L9:	sinc 15 -1;
					goto L7;
				L10:	sload 15;
					bspush 11;
					sdiv;
					sstore 16;
				L11:	sload 16;
					bspush 10;
					if_scmplt L13;
				L12:	aload 14;
					bspush 11;
					aload 14;
					sconst_0;
					bspush 99;
					invokestatic 34;		// javacard/framework/Util.arrayCopyNonAtomic([BS[BSS)S
					pop;
					bspush 9;
					sstore 16;
				L13:	sload 16;
					bspush 11;
					smul;
					sstore 17;
				L14:	aload 14;
					sload 17;
					sinc 17 1;
					sload_2;
					bastore;
					aload 14;
					sload 17;
					iload_3;
					invokestatic 47;		// HospitalCard/DataHelper.setInt([BSI)V
					sinc 17 4;
					aload 14;
					sload 17;
					iload 5;
					invokestatic 47;		// HospitalCard/DataHelper.setInt([BSI)V
					sinc 17 4;
					aload 14;
					sload 17;
					sload 7;
					invokestatic 48;		// javacard/framework/Util.setShort([BSS)S
					pop;
					sinc 17 2;
					sload 16;
					sconst_1;
					sadd;
					bspush 11;
					smul;
					sstore 18;
				L15:	sload 18;
					s2i;
					bipush 15;
					iadd;
					bipush 16;
					idiv;
					bipush 16;
					imul;
					i2s;
					sstore 19;
				L16:	sload 19;
					sconst_2;
					invokestatic 39;		// javacard/framework/JCSystem.makeTransientByteArray(SB)[B
					astore 20;
				L17:	aload 14;
					sconst_0;
					aload 20;
					sconst_0;
					sload 18;
					invokestatic 34;		// javacard/framework/Util.arrayCopyNonAtomic([BS[BSS)S
					pop;
					aload 10;
					aload 8;
					sconst_0;
					invokeinterface 3 37 4;		// javacard/security/AESKey
					aload 9;
					aload 10;
					sconst_2;
					invokevirtual 38;		// javacardx/crypto/Cipher.init(Ljavacard/security/Key;B)V
					aload 9;
					aload 20;
					sconst_0;
					sload 19;
					aload_0;
					sconst_0;
					invokevirtual 40;		// javacardx/crypto/Cipher.doFinal([BSS[BS)S
					sstore 21;
				L18:	aload 14;
					sconst_0;
					bspush 110;
					sconst_0;
					invokestatic 33;		// javacard/framework/Util.arrayFillNonAtomic([BSSB)S
					pop;
					aload 20;
					sconst_0;
					sload 19;
					sconst_0;
					invokestatic 33;		// javacard/framework/Util.arrayFillNonAtomic([BSSB)S
					pop;
					sload 21;
				L19:	sreturn;
				L20:	astore 15;
				L21:	sload_1;
					sreturn;
			.exceptionTable {
				// start_block end_block handler_block catch_type_index
				L4 L19 L20 36;
			}
		}

	}

	.class public PINHelper 2 extends 0.0 {		// extends java/lang/Object

		.publicMethodTable 1 {
			equals(Ljava/lang/Object;)Z;
		}

		.packageMethodTable 0 {
		}

		.method public <init>()V 0 {
			.stack 1;
			.locals 0;

				L0:	aload_0;
					invokespecial 101;		// java/lang/Object.<init>()V
					return;
		}

		.method public static verifyPin([BSS[B[B)Z 1 {
			.stack 5;
			.locals 1;

				L0:	bspush 20;
					sconst_2;
					invokestatic 39;		// javacard/framework/JCSystem.makeTransientByteArray(SB)[B
					astore 5;
				L1:	aload_0;
					sload_1;
					sload_2;
					aload 4;
					aload 5;
					invokestatic 49;		// HospitalCard/CryptoHelper.hashPin([BSS[B[B)S
					pop;
					aload 5;
					sconst_0;
					aload_3;
					sconst_0;
					bspush 20;
					invokestatic 51;		// javacard/framework/Util.arrayCompare([BS[BSS)B
					ifne L3;
				L2:	sconst_1;
					goto L4;
				L3:	sconst_0;
				L4:	sreturn;
		}

		.method public static createPinHash([BSS[B[B)V 2 {
			.stack 5;
			.locals 0;

				L0:	aload_0;
					sload_1;
					sload_2;
					aload_3;
					aload 4;
					invokestatic 49;		// HospitalCard/CryptoHelper.hashPin([BSS[B[B)S
					pop;
					return;
		}

		.method public static checkPinTries(B)S 3 {
			.stack 2;
			.locals 0;

				L0:	sload_0;
					ifne L2;
				L1:	sspush 27014;
					invokestatic 44;		// javacard/framework/ISOException.throwIt(S)V
				L2:	sload_0;
					sconst_1;
					ssub;
					sreturn;
		}

		.method public static throwPinTriesException(B)V 4 {
			.stack 2;
			.locals 0;

				L0:	sload_0;
					ifne L2;
				L1:	sspush 27014;
					invokestatic 44;		// javacard/framework/ISOException.throwIt(S)V
					goto L3;
				L2:	sspush 25536;
					sload_0;
					sor;
					invokestatic 44;		// javacard/framework/ISOException.throwIt(S)V
				L3:	return;
		}

		.method public static isPinDifferent([BSS[BSS)Z 5 {
			.stack 5;
			.locals 0;

				L0:	sload_2;
					sload 5;
					if_scmpeq L2;
				L1:	sconst_1;
					sreturn;
				L2:	aload_0;
					sload_1;
					aload_3;
					sload 4;
					sload_2;
					invokestatic 51;		// javacard/framework/Util.arrayCompare([BS[BSS)B
					ifeq L4;
				L3:	sconst_1;
					goto L5;
				L4:	sconst_0;
				L5:	sreturn;
		}

		.method public static safeHash(Ljavacard/security/MessageDigest;[BSS[BS)V 6 {
			.stack 6;
			.locals 1;

			.descriptor	Ljavacard/security/MessageDigest;	1.11;

				L0:	aload_0;
					invokevirtual 30;		// javacard/security/MessageDigest.reset()V
					aload_0;
					aload_1;
					sload_2;
					sload_3;
					aload 4;
					sload 5;
					invokevirtual 32;		// javacard/security/MessageDigest.doFinal([BSS[BS)S
					pop;
				L1:	goto L4;
				L2:	astore 6;
				L3:	sspush 28417;
					invokestatic 44;		// javacard/framework/ISOException.throwIt(S)V
				L4:	return;
			.exceptionTable {
				// start_block end_block handler_block catch_type_index
				L0 L1 L2 42;
			}
		}

	}

	.class public RSAHelper 3 extends 0.0 {		// extends java/lang/Object

		.publicMethodTable 1 {
			equals(Ljava/lang/Object;)Z;
		}

		.packageMethodTable 0 {
		}

		.method public <init>()V 0 {
			.stack 1;
			.locals 0;

				L0:	aload_0;
					invokespecial 101;		// java/lang/Object.<init>()V
					return;
		}

		.method public static sign(Ljavacardx/crypto/Cipher;Ljavacard/security/RSAPrivateKey;[BSS[BS)S 1 {
			.stack 6;
			.locals 1;

			.descriptor	Ljavacardx/crypto/Cipher;	3.1;
			.descriptor	Ljavacard/security/RSAPrivateKey;	1.8;

				L0:	aload_1;
					ifnull L2;
				L1:	aload_1;
					invokeinterface 1 53 3;		// javacard/security/RSAPrivateKey
					ifne L3;
				L2:	sspush 27013;
					invokestatic 44;		// javacard/framework/ISOException.throwIt(S)V
				L3:	aload_0;
					aload_1;
					sconst_2;
					invokevirtual 38;		// javacardx/crypto/Cipher.init(Ljavacard/security/Key;B)V
					aload_0;
					aload_2;
					sload_3;
					sload 4;
					aload 5;
					sload 6;
					invokevirtual 40;		// javacardx/crypto/Cipher.doFinal([BSS[BS)S
				L4:	sreturn;
				L5:	astore 7;
				L6:	sspush 28416;
					invokestatic 44;		// javacard/framework/ISOException.throwIt(S)V
					sconst_0;
					sreturn;
			.exceptionTable {
				// start_block end_block handler_block catch_type_index
				L3 L4 L5 36;
			}
		}

		.method public static verify(Ljavacardx/crypto/Cipher;Ljavacard/security/RSAPublicKey;[BSS[BSS)Z 2 {
			.stack 6;
			.locals 2;

			.descriptor	Ljavacardx/crypto/Cipher;	3.1;
			.descriptor	Ljavacard/security/RSAPublicKey;	1.9;

				L0:	aload_1;
					ifnull L2;
				L1:	aload_1;
					invokeinterface 1 55 3;		// javacard/security/RSAPublicKey
					ifne L3;
				L2:	sconst_0;
					sreturn;
				L3:	aload_0;
					aload_1;
					sconst_1;
					invokevirtual 38;		// javacardx/crypto/Cipher.init(Ljavacard/security/Key;B)V
					sspush 128;
					newarray 11;
					astore 8;
				L4:	aload_0;
					aload_2;
					sload_3;
					sload 4;
					aload 8;
					sconst_0;
					invokevirtual 40;		// javacardx/crypto/Cipher.doFinal([BSS[BS)S
					sstore 9;
				L5:	sload 9;
					sload 7;
					if_scmpeq L8;
				L6:	sconst_0;
				L7:	sreturn;
				L8:	aload 8;
					sconst_0;
					aload 5;
					sload 6;
					sload 7;
					invokestatic 51;		// javacard/framework/Util.arrayCompare([BS[BSS)B
					ifne L10;
				L9:	sconst_1;
					goto L11;
				L10:	sconst_0;
				L11:	sreturn;
				L12:	astore 8;
				L13:	sconst_0;
					sreturn;
			.exceptionTable {
				// start_block end_block handler_block catch_type_index
				L3 L7 L12 36;
				L8 L11 L12 36;
			}
		}

		.method public static getPublicKeyBytes(Ljavacard/security/RSAPublicKey;[BS)S 3 {
			.stack 4;
			.locals 3;

			.descriptor	Ljavacard/security/RSAPublicKey;	1.9;

				L0:	aload_0;
					ifnull L2;
				L1:	aload_0;
					invokeinterface 1 55 3;		// javacard/security/RSAPublicKey
					ifne L3;
				L2:	sspush 27013;
					invokestatic 44;		// javacard/framework/ISOException.throwIt(S)V
					sconst_0;
					sreturn;
				L3:	aload_0;
					aload_1;
					sload_2;
					sconst_2;
					sadd;
					invokeinterface 3 55 5;		// javacard/security/RSAPublicKey
					sstore_3;
				L4:	sload_2;
					sconst_2;
					sadd;
					sload_3;
					sadd;
					sstore 4;
				L5:	aload_0;
					aload_1;
					sload 4;
					sconst_2;
					sadd;
					invokeinterface 3 55 4;		// javacard/security/RSAPublicKey
					sstore 5;
				L6:	aload_1;
					sload_2;
					sload_3;
					invokestatic 48;		// javacard/framework/Util.setShort([BSS)S
					pop;
					aload_1;
					sload 4;
					sload 5;
					invokestatic 48;		// javacard/framework/Util.setShort([BSS)S
					pop;
					sconst_4;
					sload_3;
					sadd;
					sload 5;
					sadd;
					sreturn;
		}

		.method public static generateKeyPair(Ljavacard/security/KeyPair;)Z 4 {
			.stack 1;
			.locals 1;

			.descriptor	Ljavacard/security/KeyPair;	1.16;

				L0:	aload_0;
					ifnonnull L2;
				L1:	sconst_0;
					sreturn;
				L2:	aload_0;
					invokevirtual 58;		// javacard/security/KeyPair.getPrivate()Ljavacard/security/PrivateKey;
					checkcast 0 53;		// T_CLASSORINTERFACE javacard/security/RSAPrivateKey
					invokeinterface 1 53 3;		// javacard/security/RSAPrivateKey
					ifne L4;
				L3:	aload_0;
					invokevirtual 59;		// javacard/security/KeyPair.genKeyPair()V
				L4:	sconst_1;
				L5:	sreturn;
				L6:	astore_1;
				L7:	sconst_0;
					sreturn;
			.exceptionTable {
				// start_block end_block handler_block catch_type_index
				L2 L5 L6 36;
			}
		}

	}

	.class public UserApplet 4 extends 2.3 {		// extends javacard/framework/Applet

		.fields {
			private byte[] cardID 0;		// [B
			private byte[] hashPinUser 1;		// [B
			private byte[] hashPinAdminReset 2;		// [B
			private byte[] encUser 3;		// [B
			private byte[] encAdmin 4;		// [B
			private byte[] encPatient 5;		// [B
			private byte[] encPhoto 6;		// [B
			private byte[] encBalance 7;		// [B
			private byte[] lastTxnHash 8;		// [B
			private byte[] mkUser 9;		// [B
			private 1.16 rsaKeyPair 10;		// Ljavacard/security/KeyPair;
			private 1.8 skUser 11;		// Ljavacard/security/RSAPrivateKey;
			private 1.9 pkUser 12;		// Ljavacard/security/RSAPublicKey;
			private 3.1 rsaCipher 13;		// Ljavacardx/crypto/Cipher;
			private 1.11 sha256 14;		// Ljavacard/security/MessageDigest;
			private 3.1 aesCipher 15;		// Ljavacardx/crypto/Cipher;
			private 1.20 aesKey 16;		// Ljavacard/security/AESKey;
			private 1.14 randomData 17;		// Ljavacard/security/RandomData;
			private byte[] tempHashBuffer 18;		// [B
			private byte[] tempPinBuffer 19;		// [B
			private byte[] tempDecryptBuffer 20;		// [B
			private byte[] tempBalanceBuffer 21;		// [B
			private byte initialized 22;		// B
			private byte pinRetryCounter 23;		// B
			private byte blockedFlag 24;		// B
			private byte pinChangedFlag 25;		// B
			private short encPatientLength 26;		// S
			private short encPhotoLength 27;		// S
			private short txnCounter 28;		// S
			private static final byte CLA = -128;		// B
			private static final byte INS_GET_STATUS = 1;		// B
			private static final byte INS_ISSUE_CARD = 2;		// B
			private static final byte INS_VERIFY_PIN_AND_READ_DATA = 3;		// B
			private static final byte INS_UPDATE_PATIENT_DATA = 4;		// B
			private static final byte INS_ADMIN_RESET_PIN = 5;		// B
			private static final byte INS_CHANGE_PIN = 10;		// B
			private static final byte INS_DEBIT = 7;		// B
			private static final byte INS_GET_TXN_STATUS = 8;		// B
			private static final byte INS_CREDIT = 9;		// B
			private static final byte INS_SIGN_CHALLENGE = 16;		// B
			private static final byte INS_GET_PIN_CHANGE_STATUS = 17;		// B
			private static final byte INS_SET_PHOTO = 18;		// B
			private static final byte INS_GET_PHOTO = 19;		// B
			private static final byte MAX_PIN_TRIES = 5;		// B
			private static final short CARD_ID_LENGTH = 16;		// S
			private static final short HASH_LENGTH = 20;		// S
			private static final short MK_USER_LENGTH = 16;		// S
			private static final short MK_USER_ENC_LENGTH = 32;		// S
			private static final short MAX_PATIENT_DATA_LENGTH = 256;		// S
			private static final short MAX_PHOTO_LENGTH = 20480;		// S
			private static final short BALANCE_LENGTH = 4;		// S
			private static final short BALANCE_ENC_LENGTH = 16;		// S
			private static final short KDF_ITERATIONS = 1000;		// S
		}

		.publicMethodTable 7 {
			equals(Ljava/lang/Object;)Z;
			register()V;
			register([BSB)V;
			selectingApplet()Z;
			deselect()V;
			getShareableInterfaceObject(Ljavacard/framework/AID;B)Ljavacard/framework/Shareable;;
			select()Z;
			process(Ljavacard/framework/APDU;)V;
		}

		.packageMethodTable 0 {
		}

		.method protected <init>([BSB)V 0 {
			.stack 5;
			.locals 1;

				L0:	aload_0;
					invokespecial 99;		// javacard/framework/Applet.<init>()V
					aload_0;
					bspush 16;
					newarray 11;
					putfield_a 0;		// reference HospitalCard/UserApplet.cardID
					aload_0;
					bspush 20;
					newarray 11;
					putfield_a 1;		// reference HospitalCard/UserApplet.hashPinUser
					aload_0;
					bspush 20;
					newarray 11;
					putfield_a 2;		// reference HospitalCard/UserApplet.hashPinAdminReset
					aload_0;
					bspush 32;
					newarray 11;
					putfield_a 3;		// reference HospitalCard/UserApplet.encUser
					aload_0;
					bspush 32;
					newarray 11;
					putfield_a 4;		// reference HospitalCard/UserApplet.encAdmin
					aload_0;
					sspush 256;
					newarray 11;
					putfield_a 5;		// reference HospitalCard/UserApplet.encPatient
					aload_0;
					sspush 20480;
					newarray 11;
					putfield_a 6;		// reference HospitalCard/UserApplet.encPhoto
					aload_0;
					bspush 16;
					newarray 11;
					putfield_a 7;		// reference HospitalCard/UserApplet.encBalance
					aload_0;
					bspush 20;
					newarray 11;
					putfield_a 8;		// reference HospitalCard/UserApplet.lastTxnHash
					aload_0;
					bspush 32;
					sconst_2;
					invokestatic 39;		// javacard/framework/JCSystem.makeTransientByteArray(SB)[B
					putfield_a 9;		// reference HospitalCard/UserApplet.mkUser
					aload_0;
					bspush 20;
					sconst_2;
					invokestatic 39;		// javacard/framework/JCSystem.makeTransientByteArray(SB)[B
					putfield_a 10;		// reference HospitalCard/UserApplet.tempHashBuffer
					aload_0;
					bspush 6;
					sconst_2;
					invokestatic 39;		// javacard/framework/JCSystem.makeTransientByteArray(SB)[B
					putfield_a 11;		// reference HospitalCard/UserApplet.tempPinBuffer
					aload_0;
					sspush 256;
					sconst_2;
					invokestatic 39;		// javacard/framework/JCSystem.makeTransientByteArray(SB)[B
					putfield_a 12;		// reference HospitalCard/UserApplet.tempDecryptBuffer
					aload_0;
					bspush 16;
					sconst_2;
					invokestatic 39;		// javacard/framework/JCSystem.makeTransientByteArray(SB)[B
					putfield_a 13;		// reference HospitalCard/UserApplet.tempBalanceBuffer
					aload_0;
					sconst_0;
					putfield_b 14;		// byte HospitalCard/UserApplet.initialized
					aload_0;
					sconst_5;
					putfield_b 15;		// byte HospitalCard/UserApplet.pinRetryCounter
					aload_0;
					sconst_0;
					putfield_b 16;		// byte HospitalCard/UserApplet.blockedFlag
					aload_0;
					sconst_0;
					putfield_b 17;		// byte HospitalCard/UserApplet.pinChangedFlag
					aload_0;
					sconst_0;
					putfield_s 18;		// short HospitalCard/UserApplet.encPatientLength
					aload_0;
					sconst_0;
					putfield_s 19;		// short HospitalCard/UserApplet.encPhotoLength
					aload_0;
					sconst_0;
					putfield_s 20;		// short HospitalCard/UserApplet.txnCounter
					getfield_a_this 8;		// reference HospitalCard/UserApplet.lastTxnHash
					sconst_0;
					bspush 20;
					sconst_0;
					invokestatic 33;		// javacard/framework/Util.arrayFillNonAtomic([BSSB)S
					pop;
				L1:	aload_0;
					sconst_1;
					sconst_0;
					invokestatic 29;		// javacard/security/MessageDigest.getInstance(BZ)Ljavacard/security/MessageDigest;
					putfield_a 21;		// reference HospitalCard/UserApplet.sha256
					aload_0;
					bspush 14;
					sconst_0;
					invokestatic 50;		// javacardx/crypto/Cipher.getInstance(BZ)Ljavacardx/crypto/Cipher;
					putfield_a 22;		// reference HospitalCard/UserApplet.aesCipher
					aload_0;
					bspush 15;
					sspush 128;
					sconst_0;
					invokestatic 52;		// javacard/security/KeyBuilder.buildKey(BSZ)Ljavacard/security/Key;
					checkcast 0 37;		// T_CLASSORINTERFACE javacard/security/AESKey
					putfield_a 23;		// reference HospitalCard/UserApplet.aesKey
					aload_0;
					sconst_2;
					invokestatic 54;		// javacard/security/RandomData.getInstance(B)Ljavacard/security/RandomData;
					putfield_a 24;		// reference HospitalCard/UserApplet.randomData
					aload_0;
					new 56;		// javacard/security/KeyPair
					dup;
					sconst_1;
					sspush 1024;
					invokespecial 57;		// javacard/security/KeyPair.<init>(BS)V
					putfield_a 25;		// reference HospitalCard/UserApplet.rsaKeyPair
					aload_0;
					bspush 10;
					sconst_0;
					invokestatic 50;		// javacardx/crypto/Cipher.getInstance(BZ)Ljavacardx/crypto/Cipher;
					putfield_a 26;		// reference HospitalCard/UserApplet.rsaCipher
				L2:	goto L4;
				L3:	astore 4;
				L4:	aload_0;
					aload_1;
					sload_2;
					sconst_1;
					sadd;
					aload_1;
					sload_2;
					baload;
					invokevirtual 60;		// javacard/framework/Applet.register([BSB)V
					return;
			.exceptionTable {
				// start_block end_block handler_block catch_type_index
				L1 L2 L3 36;
			}
		}

		.method public static install([BSB)V 1 {
			.stack 5;
			.locals 0;

				L0:	new 61;		// HospitalCard/UserApplet
					dup;
					aload_0;
					sload_1;
					sload_2;
					invokespecial 62;		// HospitalCard/UserApplet.<init>([BSB)V
					pop;
					return;
		}

		.method public process(Ljavacard/framework/APDU;)V 7 {
			.stack 2;
			.locals 2;

			.descriptor	Ljavacard/framework/APDU;	2.10;

				L0:	aload_0;
					invokevirtual 63;		// javacard/framework/Applet.selectingApplet()Z
					ifeq L2;
				L1:	return;
				L2:	aload_1;
					invokevirtual 64;		// javacard/framework/APDU.getBuffer()[B
					astore_2;
				L3:	aload_2;
					sconst_0;
					baload;
					bspush -128;
					if_scmpeq L5;
				L4:	sspush 28160;
					invokestatic 44;		// javacard/framework/ISOException.throwIt(S)V
				L5:	aload_2;
					sconst_1;
					baload;
					sstore_3;
				L6:	sload_3;
					sconst_2;
					if_scmpeq L15;
				L7:	sload_3;
					sconst_3;
					if_scmpeq L15;
				L8:	sload_3;
					sconst_4;
					if_scmpeq L15;
				L9:	sload_3;
					sconst_5;
					if_scmpeq L15;
				L10:	sload_3;
					bspush 10;
					if_scmpeq L15;
				L11:	sload_3;
					bspush 9;
					if_scmpeq L15;
				L12:	sload_3;
					bspush 7;
					if_scmpeq L15;
				L13:	sload_3;
					bspush 16;
					if_scmpeq L15;
				L14:	sload_3;
					bspush 18;
					if_scmpne L16;
				L15:	aload_1;
					invokevirtual 65;		// javacard/framework/APDU.setIncomingAndReceive()S
					pop;
				L16:	sload_3;
					stableswitch L30 1 19 L17 L18 L19 L20 L21 L30 L23 L24 L25 L22 L30 L30 L30 L30 L30 L26 L27 L28 L29;
				L17:	aload_0;
					aload_1;
					invokespecial 66;		// HospitalCard/UserApplet.getStatus(Ljavacard/framework/APDU;)V
					goto L31;
				L18:	aload_0;
					aload_1;
					invokespecial 67;		// HospitalCard/UserApplet.issueCard(Ljavacard/framework/APDU;)V
					goto L31;
				L19:	aload_0;
					aload_1;
					invokespecial 68;		// HospitalCard/UserApplet.verifyPinAndReadData(Ljavacard/framework/APDU;)V
					goto L31;
				L20:	aload_0;
					aload_1;
					invokespecial 69;		// HospitalCard/UserApplet.updatePatientData(Ljavacard/framework/APDU;)V
					goto L31;
				L21:	aload_0;
					aload_1;
					invokespecial 70;		// HospitalCard/UserApplet.adminResetPin(Ljavacard/framework/APDU;)V
					goto L31;
				L22:	aload_0;
					aload_1;
					invokespecial 71;		// HospitalCard/UserApplet.changePin(Ljavacard/framework/APDU;)V
					goto L31;
				L23:	aload_0;
					aload_1;
					invokespecial 72;		// HospitalCard/UserApplet.debitTransaction(Ljavacard/framework/APDU;)V
					goto L31;
				L24:	aload_0;
					aload_1;
					invokespecial 73;		// HospitalCard/UserApplet.getTxnStatus(Ljavacard/framework/APDU;)V
					goto L31;
				L25:	aload_0;
					aload_1;
					invokespecial 74;		// HospitalCard/UserApplet.creditTransaction(Ljavacard/framework/APDU;)V
					goto L31;
				L26:	aload_0;
					aload_1;
					invokespecial 75;		// HospitalCard/UserApplet.signChallenge(Ljavacard/framework/APDU;)V
					goto L31;
				L27:	aload_0;
					aload_1;
					invokespecial 76;		// HospitalCard/UserApplet.getPinChangeStatus(Ljavacard/framework/APDU;)V
					goto L31;
				L28:	aload_0;
					aload_1;
					invokespecial 77;		// HospitalCard/UserApplet.setPhoto(Ljavacard/framework/APDU;)V
					goto L31;
				L29:	aload_0;
					aload_1;
					invokespecial 78;		// HospitalCard/UserApplet.getPhoto(Ljavacard/framework/APDU;)V
					goto L31;
				L30:	sspush 27904;
					invokestatic 44;		// javacard/framework/ISOException.throwIt(S)V
				L31:	return;
		}

		.method private getStatus(Ljavacard/framework/APDU;)V {
			.stack 5;
			.locals 2;

			.descriptor	Ljavacard/framework/APDU;	2.10;

				L0:	aload_1;
					invokevirtual 64;		// javacard/framework/APDU.getBuffer()[B
					astore_2;
				L1:	sconst_0;
					sstore_3;
				L2:	aload_2;
					sload_3;
					sinc 3 1;
					getfield_b_this 14;		// byte HospitalCard/UserApplet.initialized
					bastore;
					aload_2;
					sload_3;
					sinc 3 1;
					getfield_b_this 15;		// byte HospitalCard/UserApplet.pinRetryCounter
					bastore;
					aload_2;
					sload_3;
					sinc 3 1;
					getfield_b_this 16;		// byte HospitalCard/UserApplet.blockedFlag
					bastore;
					getfield_a_this 0;		// reference HospitalCard/UserApplet.cardID
					sconst_0;
					aload_2;
					sload_3;
					bspush 16;
					invokestatic 34;		// javacard/framework/Util.arrayCopyNonAtomic([BS[BSS)S
					pop;
					sinc 3 16;
					aload_1;
					sconst_0;
					sload_3;
					invokevirtual 79;		// javacard/framework/APDU.setOutgoingAndSend(SS)V
					return;
		}

		.method private issueCard(Ljavacard/framework/APDU;)V {
			.stack 6;
			.locals 10;

			.descriptor	Ljavacard/framework/APDU;	2.10;

				L0:	getfield_b_this 14;		// byte HospitalCard/UserApplet.initialized
					sconst_1;
					if_scmpne L2;
				L1:	sspush 27013;
					invokestatic 44;		// javacard/framework/ISOException.throwIt(S)V
				L2:	aload_1;
					invokevirtual 64;		// javacard/framework/APDU.getBuffer()[B
					astore_2;
				L3:	bspush 7;
					sconst_2;
					invokestatic 81;		// javacard/framework/JCSystem.makeTransientShortArray(SB)[S
					astore_3;
				L4:	aload_0;
					aload_2;
					aload_3;
					invokespecial 82;		// HospitalCard/UserApplet.parseIssueCardInput([B[S)V
					aload_3;
					sconst_1;
					saload;
					sstore 4;
				L5:	aload_3;
					sconst_2;
					saload;
					sstore 5;
				L6:	aload_3;
					sconst_3;
					saload;
					sstore 6;
				L7:	aload_3;
					sconst_4;
					saload;
					sstore 7;
				L8:	aload_3;
					sconst_5;
					saload;
					s2i;
					bipush 16;
					ishl;
					aload_3;
					bspush 6;
					saload;
					s2i;
					iipush 65535;
					iand;
					ior;
					istore 8;
				L9:	aload_0;
					invokespecial 83;		// HospitalCard/UserApplet.generateAndInitializeKeys()V
					aload_0;
					aload_2;
					sload 6;
					sload 7;
					invokespecial 84;		// HospitalCard/UserApplet.setupPINsAndEncryptMK([BSS)V
					aload_0;
					aload_2;
					sload 4;
					sload 5;
					invokespecial 85;		// HospitalCard/UserApplet.encryptAndStorePatientData([BSS)V
					aload_0;
					iload 8;
					invokespecial 86;		// HospitalCard/UserApplet.encryptAndStoreBalance(I)V
					aload_0;
					sconst_1;
					putfield_b 14;		// byte HospitalCard/UserApplet.initialized
					aload_0;
					sconst_0;
					putfield_b 17;		// byte HospitalCard/UserApplet.pinChangedFlag
					getfield_a_this 9;		// reference HospitalCard/UserApplet.mkUser
					sconst_0;
					bspush 32;
					sconst_0;
					invokestatic 33;		// javacard/framework/Util.arrayFillNonAtomic([BSSB)S
					pop;
					aload_0;
					aload_2;
					invokespecial 87;		// HospitalCard/UserApplet.buildIssueCardResponse([B)S
					sstore 10;
				L10:	aload_1;
					sconst_0;
					sload 10;
					invokevirtual 79;		// javacard/framework/APDU.setOutgoingAndSend(SS)V
				L11:	goto L14;
				L12:	astore 11;
				L13:	sspush 28465;
					invokestatic 44;		// javacard/framework/ISOException.throwIt(S)V
				L14:	goto L23;
				L15:	astore_3;
				L16:	sspush 28448;
					aload_3;
					invokevirtual 43;		// javacard/security/CryptoException.getReason()S
					bspush 15;
					sand;
					sor;
					invokestatic 44;		// javacard/framework/ISOException.throwIt(S)V
				L17:	goto L23;
				L18:	astore_3;
				L19:	sspush 28464;
					invokestatic 44;		// javacard/framework/ISOException.throwIt(S)V
				L20:	goto L23;
				L21:	astore_3;
				L22:	sspush 28416;
					invokestatic 44;		// javacard/framework/ISOException.throwIt(S)V
				L23:	return;
			.exceptionTable {
				// start_block end_block handler_block catch_type_index
				L10 L11 L12 36;
				L3 L14 L15 42;
				L3 L14 L18 80;
				L3 L14 L21 36;
			}
		}

		.method private verifyPinAndReadData(Ljavacard/framework/APDU;)V {
			.stack 5;
			.locals 5;

			.descriptor	Ljavacard/framework/APDU;	2.10;

				L0:	getfield_b_this 14;		// byte HospitalCard/UserApplet.initialized
					sconst_1;
					if_scmpeq L2;
				L1:	sspush 27013;
					invokestatic 44;		// javacard/framework/ISOException.throwIt(S)V
				L2:	getfield_b_this 16;		// byte HospitalCard/UserApplet.blockedFlag
					sconst_1;
					if_scmpne L4;
				L3:	sspush 27011;
					invokestatic 44;		// javacard/framework/ISOException.throwIt(S)V
				L4:	aload_1;
					invokevirtual 64;		// javacard/framework/APDU.getBuffer()[B
					astore_2;
				L5:	sconst_5;
					sstore_3;
				L6:	bspush 6;
					sstore 4;
				L7:	aload_0;
					aload_2;
					sload_3;
					sload 4;
					invokespecial 90;		// HospitalCard/UserApplet.validateAndVerifyPIN([BSS)V
				L8:	goto L13;
				L9:	astore 5;
				L10:	aload 5;
					athrow;
				L11:	astore 5;
				L12:	sspush 28586;
					invokestatic 44;		// javacard/framework/ISOException.throwIt(S)V
				L13:	sconst_0;
					sstore 5;
				L14:	aload_0;
					aload_2;
					sload_3;
					sload 4;
					aload_1;
					invokespecial 91;		// HospitalCard/UserApplet.decryptDataAndBuildResponse([BSSLjavacard/framework/APDU;)S
					sstore 5;
				L15:	goto L20;
				L16:	astore 6;
				L17:	aload 6;
					athrow;
				L18:	astore 6;
				L19:	sspush 28587;
					invokestatic 44;		// javacard/framework/ISOException.throwIt(S)V
				L20:	aload_1;
					sconst_0;
					sload 5;
					invokevirtual 79;		// javacard/framework/APDU.setOutgoingAndSend(SS)V
				L21:	goto L24;
				L22:	astore 6;
				L23:	sspush 28585;
					invokestatic 44;		// javacard/framework/ISOException.throwIt(S)V
				L24:	goto L42;
				L25:	astore 5;
				L26:	aload 5;
					invokevirtual 92;		// javacard/framework/ISOException.getReason()S
					invokestatic 44;		// javacard/framework/ISOException.throwIt(S)V
				L27:	goto L42;
				L28:	astore 5;
				L29:	aload 5;
					invokevirtual 43;		// javacard/security/CryptoException.getReason()S
					sstore 6;
				L30:	sload 6;
					ifne L32;
				L31:	sspush 28416;
					invokestatic 44;		// javacard/framework/ISOException.throwIt(S)V
					goto L33;
				L32:	sspush 28416;
					sload 6;
					bspush 15;
					sand;
					sor;
					invokestatic 44;		// javacard/framework/ISOException.throwIt(S)V
				L33:	goto L42;
				L34:	astore 5;
				L35:	sspush 28464;
					invokestatic 44;		// javacard/framework/ISOException.throwIt(S)V
				L36:	goto L42;
				L37:	astore 5;
				L38:	sspush 28496;
					invokestatic 44;		// javacard/framework/ISOException.throwIt(S)V
				L39:	goto L42;
				L40:	astore 5;
				L41:	sspush 28568;
					invokestatic 44;		// javacard/framework/ISOException.throwIt(S)V
				L42:	return;
			.exceptionTable {
				// start_block end_block handler_block catch_type_index
				L7 L8 L9 88;
				L7 L8 L11 36;
				L14 L15 L16 88;
				L14 L15 L18 36;
				L20 L21 L22 36;
				L7 L24 L25 88;
				L7 L24 L28 42;
				L7 L24 L34 80;
				L7 L24 L37 89;
				L7 L24 L40 36;
			}
		}

		.method private updatePatientData(Ljavacard/framework/APDU;)V {
			.stack 7;
			.locals 5;

			.descriptor	Ljavacard/framework/APDU;	2.10;

				L0:	getfield_b_this 14;		// byte HospitalCard/UserApplet.initialized
					sconst_1;
					if_scmpeq L2;
				L1:	sspush 27013;
					invokestatic 44;		// javacard/framework/ISOException.throwIt(S)V
				L2:	aload_0;
					invokespecial 93;		// HospitalCard/UserApplet.isMasterKeyValid()Z
					ifne L4;
				L3:	sspush 27010;
					invokestatic 44;		// javacard/framework/ISOException.throwIt(S)V
				L4:	aload_1;
					invokevirtual 64;		// javacard/framework/APDU.getBuffer()[B
					astore_2;
				L5:	sconst_5;
					sstore_3;
				L6:	aload_2;
					sload_3;
					invokestatic 45;		// javacard/framework/Util.getShort([BS)S
					sstore 4;
				L7:	sinc 3 2;
					sload 4;
					ifle L9;
				L8:	sload 4;
					sspush 256;
					if_scmple L10;
				L9:	sspush 26368;
					invokestatic 44;		// javacard/framework/ISOException.throwIt(S)V
				L10:	getfield_a_this 23;		// reference HospitalCard/UserApplet.aesKey
					getfield_a_this 9;		// reference HospitalCard/UserApplet.mkUser
					sconst_0;
					invokeinterface 3 37 4;		// javacard/security/AESKey
					getfield_a_this 22;		// reference HospitalCard/UserApplet.aesCipher
					getfield_a_this 23;		// reference HospitalCard/UserApplet.aesKey
					sconst_2;
					invokevirtual 38;		// javacardx/crypto/Cipher.init(Ljavacard/security/Key;B)V
					sload 4;
					s2i;
					bipush 15;
					iadd;
					bipush 16;
					idiv;
					bipush 16;
					imul;
					i2s;
					sstore 5;
				L11:	sload 5;
					sconst_2;
					invokestatic 39;		// javacard/framework/JCSystem.makeTransientByteArray(SB)[B
					astore 6;
				L12:	aload_2;
					sload_3;
					aload 6;
					sconst_0;
					sload 4;
					invokestatic 34;		// javacard/framework/Util.arrayCopyNonAtomic([BS[BSS)S
					pop;
					aload_0;
					getfield_a_this 22;		// reference HospitalCard/UserApplet.aesCipher
					aload 6;
					sconst_0;
					sload 5;
					getfield_a_this 5;		// reference HospitalCard/UserApplet.encPatient
					sconst_0;
					invokevirtual 40;		// javacardx/crypto/Cipher.doFinal([BSS[BS)S
					putfield_s 18;		// short HospitalCard/UserApplet.encPatientLength
					aload_2;
					sconst_0;
					sconst_0;
					bastore;
					aload_1;
					sconst_0;
					sconst_1;
					invokevirtual 79;		// javacard/framework/APDU.setOutgoingAndSend(SS)V
				L13:	goto L16;
				L14:	astore 4;
				L15:	sspush 28416;
					aload 4;
					invokevirtual 43;		// javacard/security/CryptoException.getReason()S
					sor;
					invokestatic 44;		// javacard/framework/ISOException.throwIt(S)V
				L16:	return;
			.exceptionTable {
				// start_block end_block handler_block catch_type_index
				L6 L13 L14 42;
			}
		}

		.method private changePin(Ljavacard/framework/APDU;)V {
			.stack 7;
			.locals 7;

			.descriptor	Ljavacard/framework/APDU;	2.10;

				L0:	getfield_b_this 14;		// byte HospitalCard/UserApplet.initialized
					sconst_1;
					if_scmpeq L2;
				L1:	sspush 27013;
					invokestatic 44;		// javacard/framework/ISOException.throwIt(S)V
				L2:	getfield_b_this 16;		// byte HospitalCard/UserApplet.blockedFlag
					sconst_1;
					if_scmpne L4;
				L3:	sspush 27011;
					invokestatic 44;		// javacard/framework/ISOException.throwIt(S)V
				L4:	aload_1;
					invokevirtual 64;		// javacard/framework/APDU.getBuffer()[B
					astore_2;
				L5:	sconst_5;
					sstore_3;
				L6:	sload_3;
					sstore 4;
				L7:	bspush 6;
					sstore 5;
				L8:	sload_3;
					sload 5;
					sadd;
					sstore_3;
					sload_3;
					sstore 6;
				L9:	bspush 6;
					sstore 7;
				L10:	getfield_a_this 10;		// reference HospitalCard/UserApplet.tempHashBuffer
					sconst_0;
					bspush 20;
					sconst_0;
					invokestatic 33;		// javacard/framework/Util.arrayFillNonAtomic([BSSB)S
					pop;
				L11:	aload_0;
					aload_2;
					sload 4;
					sload 5;
					sload 6;
					sload 7;
					getfield_a_this 10;		// reference HospitalCard/UserApplet.tempHashBuffer
					invokespecial 94;		// HospitalCard/UserApplet.validatePINChange([BSSSS[B)V
				L12:	goto L17;
				L13:	astore 8;
				L14:	aload 8;
					athrow;
				L15:	astore 8;
				L16:	sspush 28592;
					invokestatic 44;		// javacard/framework/ISOException.throwIt(S)V
				L17:	aload_0;
					aload_2;
					sload 4;
					sload 5;
					sload 6;
					sload 7;
					getfield_a_this 10;		// reference HospitalCard/UserApplet.tempHashBuffer
					invokespecial 95;		// HospitalCard/UserApplet.reEncryptMasterKeyWithNewPIN([BSSSS[B)V
				L18:	goto L23;
				L19:	astore 8;
				L20:	aload 8;
					athrow;
				L21:	astore 8;
				L22:	sspush 28593;
					invokestatic 44;		// javacard/framework/ISOException.throwIt(S)V
				L23:	aload_2;
					sconst_0;
					sconst_0;
					bastore;
					aload_1;
					sconst_0;
					sconst_1;
					invokevirtual 79;		// javacard/framework/APDU.setOutgoingAndSend(SS)V
				L24:	goto L33;
				L25:	astore 8;
				L26:	aload 8;
					invokevirtual 92;		// javacard/framework/ISOException.getReason()S
					invokestatic 44;		// javacard/framework/ISOException.throwIt(S)V
				L27:	goto L33;
				L28:	astore 8;
				L29:	sspush 28416;
					aload 8;
					invokevirtual 43;		// javacard/security/CryptoException.getReason()S
					sor;
					invokestatic 44;		// javacard/framework/ISOException.throwIt(S)V
				L30:	goto L33;
				L31:	astore 8;
				L32:	sspush 28569;
					invokestatic 44;		// javacard/framework/ISOException.throwIt(S)V
				L33:	return;
			.exceptionTable {
				// start_block end_block handler_block catch_type_index
				L11 L12 L13 88;
				L11 L12 L15 36;
				L17 L18 L19 88;
				L17 L18 L21 36;
				L10 L24 L25 88;
				L10 L24 L28 42;
				L10 L24 L31 36;
			}
		}

		.method private adminResetPin(Ljavacard/framework/APDU;)V {
			.stack 14;
			.locals 10;

			.descriptor	Ljavacard/framework/APDU;	2.10;

				L0:	getfield_b_this 14;		// byte HospitalCard/UserApplet.initialized
					sconst_1;
					if_scmpeq L2;
				L1:	sspush 27013;
					invokestatic 44;		// javacard/framework/ISOException.throwIt(S)V
				L2:	aload_1;
					invokevirtual 64;		// javacard/framework/APDU.getBuffer()[B
					astore_2;
				L3:	sconst_5;
					sstore_3;
				L4:	sload_3;
					sstore 4;
				L5:	bspush 6;
					sstore 5;
				L6:	sload_3;
					sload 5;
					sadd;
					sstore_3;
					sload_3;
					sstore 6;
				L7:	bspush 6;
					sstore 7;
				L8:	bspush 20;
					sconst_2;
					invokestatic 39;		// javacard/framework/JCSystem.makeTransientByteArray(SB)[B
					astore 8;
				L9:	getfield_a_this 21;		// reference HospitalCard/UserApplet.sha256
					aload_2;
					sload 4;
					sload 5;
					aload 8;
					sconst_0;
					invokestatic 96;		// HospitalCard/PINHelper.safeHash(Ljavacard/security/MessageDigest;[BSS[BS)V
					aload 8;
					sconst_0;
					getfield_a_this 2;		// reference HospitalCard/UserApplet.hashPinAdminReset
					sconst_0;
					bspush 20;
					invokestatic 51;		// javacard/framework/Util.arrayCompare([BS[BSS)B
					ifeq L11;
				L10:	sspush 25344;
					invokestatic 44;		// javacard/framework/ISOException.throwIt(S)V
				L11:	aload_2;
					sload 4;
					sload 5;
					getfield_a_this 0;		// reference HospitalCard/UserApplet.cardID
					sconst_0;
					bspush 16;
					sspush 1000;
					getfield_a_this 4;		// reference HospitalCard/UserApplet.encAdmin
					getfield_a_this 9;		// reference HospitalCard/UserApplet.mkUser
					getfield_a_this 22;		// reference HospitalCard/UserApplet.aesCipher
					getfield_a_this 23;		// reference HospitalCard/UserApplet.aesKey
					getfield_a_this 21;		// reference HospitalCard/UserApplet.sha256
					getfield_a_this 12;		// reference HospitalCard/UserApplet.tempDecryptBuffer
					sconst_0;
					invokestatic 97;		// HospitalCard/CryptoHelper.unwrapMasterKeyWithPIN([BSS[BSSS[B[BLjavacardx/crypto/Cipher;Ljavacard/security/AESKey;Ljavacard/security/MessageDigest;[BS)Z
					sstore 9;
				L12:	sload 9;
					ifne L14;
				L13:	sspush 28420;
					invokestatic 44;		// javacard/framework/ISOException.throwIt(S)V
				L14:	getfield_a_this 25;		// reference HospitalCard/UserApplet.rsaKeyPair
					invokestatic 98;		// HospitalCard/RSAHelper.generateKeyPair(Ljavacard/security/KeyPair;)Z
					ifne L16;
				L15:	sspush 28417;
					invokestatic 44;		// javacard/framework/ISOException.throwIt(S)V
				L16:	aload_0;
					getfield_a_this 25;		// reference HospitalCard/UserApplet.rsaKeyPair
					invokevirtual 58;		// javacard/security/KeyPair.getPrivate()Ljavacard/security/PrivateKey;
					checkcast 0 53;		// T_CLASSORINTERFACE javacard/security/RSAPrivateKey
					putfield_a 27;		// reference HospitalCard/UserApplet.skUser
					aload_0;
					getfield_a_this 25;		// reference HospitalCard/UserApplet.rsaKeyPair
					invokevirtual 100;		// javacard/security/KeyPair.getPublic()Ljavacard/security/PublicKey;
					checkcast 0 55;		// T_CLASSORINTERFACE javacard/security/RSAPublicKey
					putfield_a 28;		// reference HospitalCard/UserApplet.pkUser
					getfield_a_this 27;		// reference HospitalCard/UserApplet.skUser
					ifnull L20;
				L17:	getfield_a_this 28;		// reference HospitalCard/UserApplet.pkUser
					ifnull L20;
				L18:	getfield_a_this 27;		// reference HospitalCard/UserApplet.skUser
					invokeinterface 1 53 3;		// javacard/security/RSAPrivateKey
					ifeq L20;
				L19:	getfield_a_this 28;		// reference HospitalCard/UserApplet.pkUser
					invokeinterface 1 55 3;		// javacard/security/RSAPublicKey
					ifne L21;
				L20:	sspush 28417;
					invokestatic 44;		// javacard/framework/ISOException.throwIt(S)V
				L21:	goto L24;
				L22:	astore 10;
				L23:	sspush 28432;
					aload 10;
					invokevirtual 43;		// javacard/security/CryptoException.getReason()S
					bspush 15;
					sand;
					sor;
					invokestatic 44;		// javacard/framework/ISOException.throwIt(S)V
				L24:	aload_2;
					sload 6;
					sload 7;
					getfield_a_this 0;		// reference HospitalCard/UserApplet.cardID
					sconst_0;
					bspush 16;
					sspush 1000;
					getfield_a_this 9;		// reference HospitalCard/UserApplet.mkUser
					getfield_a_this 3;		// reference HospitalCard/UserApplet.encUser
					getfield_a_this 22;		// reference HospitalCard/UserApplet.aesCipher
					getfield_a_this 23;		// reference HospitalCard/UserApplet.aesKey
					getfield_a_this 21;		// reference HospitalCard/UserApplet.sha256
					getfield_a_this 12;		// reference HospitalCard/UserApplet.tempDecryptBuffer
					sconst_0;
					invokestatic 102;		// HospitalCard/CryptoHelper.wrapMasterKeyWithPIN([BSS[BSSS[B[BLjavacardx/crypto/Cipher;Ljavacard/security/AESKey;Ljavacard/security/MessageDigest;[BS)V
					getfield_a_this 21;		// reference HospitalCard/UserApplet.sha256
					aload_2;
					sload 6;
					sload 7;
					getfield_a_this 1;		// reference HospitalCard/UserApplet.hashPinUser
					sconst_0;
					invokestatic 96;		// HospitalCard/PINHelper.safeHash(Ljavacard/security/MessageDigest;[BSS[BS)V
					aload_0;
					sconst_5;
					putfield_b 15;		// byte HospitalCard/UserApplet.pinRetryCounter
					aload_0;
					sconst_0;
					putfield_b 16;		// byte HospitalCard/UserApplet.blockedFlag
					aload_0;
					sconst_0;
					putfield_b 17;		// byte HospitalCard/UserApplet.pinChangedFlag
					getfield_a_this 9;		// reference HospitalCard/UserApplet.mkUser
					sconst_0;
					bspush 32;
					sconst_0;
					invokestatic 33;		// javacard/framework/Util.arrayFillNonAtomic([BSSB)S
					pop;
					sconst_0;
					sstore 10;
				L25:	aload_2;
					sload 10;
					sinc 10 1;
					sconst_0;
					bastore;
				L26:	getfield_a_this 28;		// reference HospitalCard/UserApplet.pkUser
					aload_2;
					sload 10;
					invokestatic 103;		// HospitalCard/RSAHelper.getPublicKeyBytes(Ljavacard/security/RSAPublicKey;[BS)S
					sstore 11;
				L27:	sload 10;
					sload 11;
					sadd;
					sstore 10;
				L28:	goto L30;
				L29:	astore 11;
				L30:	aload_1;
					sconst_0;
					sload 10;
					invokevirtual 79;		// javacard/framework/APDU.setOutgoingAndSend(SS)V
				L31:	goto L34;
				L32:	astore 8;
				L33:	sspush 28416;
					aload 8;
					invokevirtual 43;		// javacard/security/CryptoException.getReason()S
					sor;
					invokestatic 44;		// javacard/framework/ISOException.throwIt(S)V
				L34:	return;
			.exceptionTable {
				// start_block end_block handler_block catch_type_index
				L14 L21 L22 42;
				L26 L28 L29 36;
				L8 L31 L32 42;
			}
		}

		.method private isMasterKeyValid()Z {
			.stack 2;
			.locals 1;

				L0:	sconst_0;
					sstore_1;
				L1:	sload_1;
					bspush 16;
					if_scmpge L5;
				L2:	getfield_a_this 9;		// reference HospitalCard/UserApplet.mkUser
					sload_1;
					baload;
					ifeq L4;
				L3:	sconst_1;
					sreturn;
				L4:	sinc 1 1;
					goto L1;
				L5:	sconst_0;
					sreturn;
		}

		.method private signChallenge(Ljavacard/framework/APDU;)V {
			.stack 7;
			.locals 4;

			.descriptor	Ljavacard/framework/APDU;	2.10;

				L0:	getfield_b_this 14;		// byte HospitalCard/UserApplet.initialized
					sconst_1;
					if_scmpeq L2;
				L1:	sspush 27013;
					invokestatic 44;		// javacard/framework/ISOException.throwIt(S)V
				L2:	aload_0;
					invokespecial 93;		// HospitalCard/UserApplet.isMasterKeyValid()Z
					ifne L4;
				L3:	sspush 27010;
					invokestatic 44;		// javacard/framework/ISOException.throwIt(S)V
				L4:	aload_1;
					invokevirtual 64;		// javacard/framework/APDU.getBuffer()[B
					astore_2;
				L5:	aload_2;
					sconst_4;
					baload;
					sspush 255;
					sand;
					sstore_3;
				L6:	sconst_5;
					sstore 4;
				L7:	sload_3;
					ifle L9;
				L8:	sload_3;
					bspush 117;
					if_scmple L10;
				L9:	sspush 26368;
					invokestatic 44;		// javacard/framework/ISOException.throwIt(S)V
				L10:	getfield_a_this 10;		// reference HospitalCard/UserApplet.tempHashBuffer
					sconst_0;
					bspush 20;
					sconst_0;
					invokestatic 33;		// javacard/framework/Util.arrayFillNonAtomic([BSSB)S
					pop;
					getfield_a_this 21;		// reference HospitalCard/UserApplet.sha256
					invokevirtual 30;		// javacard/security/MessageDigest.reset()V
					getfield_a_this 21;		// reference HospitalCard/UserApplet.sha256
					aload_2;
					sload 4;
					sload_3;
					getfield_a_this 10;		// reference HospitalCard/UserApplet.tempHashBuffer
					sconst_0;
					invokevirtual 32;		// javacard/security/MessageDigest.doFinal([BSS[BS)S
					pop;
					getfield_a_this 26;		// reference HospitalCard/UserApplet.rsaCipher
					getfield_a_this 27;		// reference HospitalCard/UserApplet.skUser
					getfield_a_this 10;		// reference HospitalCard/UserApplet.tempHashBuffer
					sconst_0;
					bspush 20;
					aload_2;
					sconst_0;
					invokestatic 104;		// HospitalCard/RSAHelper.sign(Ljavacardx/crypto/Cipher;Ljavacard/security/RSAPrivateKey;[BSS[BS)S
					sstore 5;
				L11:	aload_1;
					sconst_0;
					sload 5;
					invokevirtual 79;		// javacard/framework/APDU.setOutgoingAndSend(SS)V
				L12:	goto L15;
				L13:	astore 5;
				L14:	sspush 28416;
					aload 5;
					invokevirtual 43;		// javacard/security/CryptoException.getReason()S
					sor;
					invokestatic 44;		// javacard/framework/ISOException.throwIt(S)V
				L15:	return;
			.exceptionTable {
				// start_block end_block handler_block catch_type_index
				L10 L12 L13 42;
			}
		}

		.method private processTransaction(Ljavacard/framework/APDU;Z)V {
			.stack 6;
			.locals 13;

			.descriptor	Ljavacard/framework/APDU;	2.10;

				L0:	getfield_b_this 14;		// byte HospitalCard/UserApplet.initialized
					sconst_1;
					if_scmpeq L2;
				L1:	sspush 27013;
					invokestatic 44;		// javacard/framework/ISOException.throwIt(S)V
				L2:	getfield_b_this 16;		// byte HospitalCard/UserApplet.blockedFlag
					sconst_1;
					if_scmpne L4;
				L3:	sspush 27011;
					invokestatic 44;		// javacard/framework/ISOException.throwIt(S)V
				L4:	aload_0;
					invokespecial 93;		// HospitalCard/UserApplet.isMasterKeyValid()Z
					ifne L6;
				L5:	sspush 27010;
					invokestatic 44;		// javacard/framework/ISOException.throwIt(S)V
				L6:	aload_1;
					invokevirtual 64;		// javacard/framework/APDU.getBuffer()[B
					astore_3;
				L7:	sconst_5;
					sstore 4;
				L8:	aload_3;
					sload 4;
					invokestatic 105;		// HospitalCard/DataHelper.getInt([BS)I
					istore 5;
				L9:	sinc 4 4;
					iload 5;
					iconst_0;
					icmp;
					ifgt L11;
				L10:	sspush 27264;
					invokestatic 44;		// javacard/framework/ISOException.throwIt(S)V
				L11:	bspush 16;
					sconst_2;
					invokestatic 39;		// javacard/framework/JCSystem.makeTransientByteArray(SB)[B
					astore 7;
				L12:	getfield_a_this 23;		// reference HospitalCard/UserApplet.aesKey
					getfield_a_this 9;		// reference HospitalCard/UserApplet.mkUser
					sconst_0;
					invokeinterface 3 37 4;		// javacard/security/AESKey
					getfield_a_this 22;		// reference HospitalCard/UserApplet.aesCipher
					getfield_a_this 23;		// reference HospitalCard/UserApplet.aesKey
					sconst_1;
					invokevirtual 38;		// javacardx/crypto/Cipher.init(Ljavacard/security/Key;B)V
					getfield_a_this 22;		// reference HospitalCard/UserApplet.aesCipher
					getfield_a_this 7;		// reference HospitalCard/UserApplet.encBalance
					sconst_0;
					bspush 16;
					aload 7;
					sconst_0;
					invokevirtual 40;		// javacardx/crypto/Cipher.doFinal([BSS[BS)S
					pop;
					aload 7;
					sconst_0;
					invokestatic 105;		// HospitalCard/DataHelper.getInt([BS)I
					istore 8;
				L13:	iload 8;
					iconst_0;
					icmp;
					ifge L15;
				L14:	iconst_0;
					istore 8;
				L15:	sload_2;
					ifeq L21;
				L16:	iload 5;
					iconst_0;
					icmp;
					ifle L19;
				L17:	iload 8;
					iipush 2147483647;
					iload 5;
					isub;
					icmp;
					ifle L19;
				L18:	sspush 27264;
					invokestatic 44;		// javacard/framework/ISOException.throwIt(S)V
				L19:	iload 8;
					iload 5;
					iadd;
					istore 10;
				L20:	goto L28;
				L21:	iload 5;
					iconst_0;
					icmp;
					ifge L23;
				L22:	sspush 27264;
					invokestatic 44;		// javacard/framework/ISOException.throwIt(S)V
				L23:	iload 5;
					iload 8;
					icmp;
					ifle L25;
				L24:	sspush 27264;
					invokestatic 44;		// javacard/framework/ISOException.throwIt(S)V
				L25:	iload 8;
					iload 5;
					isub;
					istore 10;
				L26:	iload 10;
					iconst_0;
					icmp;
					ifge L28;
				L27:	iconst_0;
					istore 10;
				L28:	getfield_s_this 20;		// short HospitalCard/UserApplet.txnCounter
					s2i;
					iipush 65535;
					icmp;
					iflt L30;
				L29:	sspush 27264;
					invokestatic 44;		// javacard/framework/ISOException.throwIt(S)V
				L30:	aload_0;
					getfield_s_this 20;		// short HospitalCard/UserApplet.txnCounter
					sconst_1;
					sadd;
					putfield_s 20;		// short HospitalCard/UserApplet.txnCounter
					bspush 31;
					sconst_2;
					invokestatic 39;		// javacard/framework/JCSystem.makeTransientByteArray(SB)[B
					astore 12;
				L31:	sconst_0;
					sstore 13;
				L32:	getfield_a_this 8;		// reference HospitalCard/UserApplet.lastTxnHash
					sconst_0;
					aload 12;
					sload 13;
					bspush 20;
					invokestatic 34;		// javacard/framework/Util.arrayCopyNonAtomic([BS[BSS)S
					pop;
					sinc 13 20;
					aload 12;
					sload 13;
					getfield_s_this 20;		// short HospitalCard/UserApplet.txnCounter
					invokestatic 48;		// javacard/framework/Util.setShort([BSS)S
					pop;
					sinc 13 2;
					aload 12;
					sload 13;
					sinc 13 1;
					sload_2;
					ifeq L34;
				L33:	sconst_1;
					goto L35;
				L34:	sconst_2;
				L35:	bastore;
					aload 12;
					sload 13;
					iload 5;
					invokestatic 47;		// HospitalCard/DataHelper.setInt([BSI)V
					sinc 13 4;
					aload 12;
					sload 13;
					iload 10;
					invokestatic 47;		// HospitalCard/DataHelper.setInt([BSI)V
					sinc 13 4;
					getfield_a_this 21;		// reference HospitalCard/UserApplet.sha256
					invokevirtual 30;		// javacard/security/MessageDigest.reset()V
					getfield_a_this 21;		// reference HospitalCard/UserApplet.sha256
					aload 12;
					sconst_0;
					sload 13;
					getfield_a_this 8;		// reference HospitalCard/UserApplet.lastTxnHash
					sconst_0;
					invokevirtual 32;		// javacard/security/MessageDigest.doFinal([BSS[BS)S
					sstore 14;
				L36:	sload 14;
					bspush 20;
					if_scmpeq L38;
				L37:	sspush 28419;
					invokestatic 44;		// javacard/framework/ISOException.throwIt(S)V
				L38:	aload 7;
					sconst_0;
					bspush 16;
					sconst_0;
					invokestatic 33;		// javacard/framework/Util.arrayFillNonAtomic([BSSB)S
					pop;
					aload 7;
					sconst_0;
					iload 10;
					invokestatic 47;		// HospitalCard/DataHelper.setInt([BSI)V
					getfield_a_this 23;		// reference HospitalCard/UserApplet.aesKey
					getfield_a_this 9;		// reference HospitalCard/UserApplet.mkUser
					sconst_0;
					invokeinterface 3 37 4;		// javacard/security/AESKey
					getfield_a_this 22;		// reference HospitalCard/UserApplet.aesCipher
					getfield_a_this 23;		// reference HospitalCard/UserApplet.aesKey
					sconst_2;
					invokevirtual 38;		// javacardx/crypto/Cipher.init(Ljavacard/security/Key;B)V
					getfield_a_this 22;		// reference HospitalCard/UserApplet.aesCipher
					aload 7;
					sconst_0;
					bspush 16;
					getfield_a_this 7;		// reference HospitalCard/UserApplet.encBalance
					sconst_0;
					invokevirtual 40;		// javacardx/crypto/Cipher.doFinal([BSS[BS)S
					pop;
					sconst_0;
					sstore 15;
				L39:	aload_3;
					sload 15;
					sinc 15 1;
					sconst_0;
					bastore;
					aload_3;
					sload 15;
					getfield_s_this 20;		// short HospitalCard/UserApplet.txnCounter
					invokestatic 48;		// javacard/framework/Util.setShort([BSS)S
					pop;
					sinc 15 2;
					aload_3;
					sload 15;
					iload 10;
					invokestatic 47;		// HospitalCard/DataHelper.setInt([BSI)V
					sinc 15 4;
					getfield_a_this 8;		// reference HospitalCard/UserApplet.lastTxnHash
					sconst_0;
					aload_3;
					sload 15;
					bspush 20;
					invokestatic 34;		// javacard/framework/Util.arrayCopyNonAtomic([BS[BSS)S
					pop;
					sinc 15 20;
					aload 7;
					sconst_0;
					bspush 16;
					sconst_0;
					invokestatic 33;		// javacard/framework/Util.arrayFillNonAtomic([BSSB)S
					pop;
					aload 12;
					sconst_0;
					bspush 31;
					sconst_0;
					invokestatic 33;		// javacard/framework/Util.arrayFillNonAtomic([BSSB)S
					pop;
					aload_1;
					sconst_0;
					sload 15;
					invokevirtual 79;		// javacard/framework/APDU.setOutgoingAndSend(SS)V
				L40:	goto L43;
				L41:	astore 5;
				L42:	sspush 28416;
					aload 5;
					invokevirtual 43;		// javacard/security/CryptoException.getReason()S
					sor;
					invokestatic 44;		// javacard/framework/ISOException.throwIt(S)V
				L43:	return;
			.exceptionTable {
				// start_block end_block handler_block catch_type_index
				L8 L40 L41 42;
			}
		}

		.method private creditTransaction(Ljavacard/framework/APDU;)V {
			.stack 3;
			.locals 0;

			.descriptor	Ljavacard/framework/APDU;	2.10;

				L0:	aload_0;
					aload_1;
					sconst_1;
					invokespecial 106;		// HospitalCard/UserApplet.processTransaction(Ljavacard/framework/APDU;Z)V
					return;
		}

		.method private debitTransaction(Ljavacard/framework/APDU;)V {
			.stack 3;
			.locals 0;

			.descriptor	Ljavacard/framework/APDU;	2.10;

				L0:	aload_0;
					aload_1;
					sconst_0;
					invokespecial 106;		// HospitalCard/UserApplet.processTransaction(Ljavacard/framework/APDU;Z)V
					return;
		}

		.method private getTxnStatus(Ljavacard/framework/APDU;)V {
			.stack 5;
			.locals 2;

			.descriptor	Ljavacard/framework/APDU;	2.10;

				L0:	getfield_b_this 14;		// byte HospitalCard/UserApplet.initialized
					sconst_1;
					if_scmpeq L2;
				L1:	sspush 27013;
					invokestatic 44;		// javacard/framework/ISOException.throwIt(S)V
				L2:	aload_1;
					invokevirtual 64;		// javacard/framework/APDU.getBuffer()[B
					astore_2;
				L3:	sconst_0;
					sstore_3;
				L4:	aload_2;
					sload_3;
					getfield_s_this 20;		// short HospitalCard/UserApplet.txnCounter
					invokestatic 48;		// javacard/framework/Util.setShort([BSS)S
					pop;
					sinc 3 2;
					getfield_a_this 8;		// reference HospitalCard/UserApplet.lastTxnHash
					sconst_0;
					aload_2;
					sload_3;
					bspush 20;
					invokestatic 34;		// javacard/framework/Util.arrayCopyNonAtomic([BS[BSS)S
					pop;
					sinc 3 20;
					aload_1;
					sconst_0;
					sload_3;
					invokevirtual 79;		// javacard/framework/APDU.setOutgoingAndSend(SS)V
					return;
		}

		.method private getPinChangeStatus(Ljavacard/framework/APDU;)V {
			.stack 3;
			.locals 1;

			.descriptor	Ljavacard/framework/APDU;	2.10;

				L0:	aload_1;
					invokevirtual 64;		// javacard/framework/APDU.getBuffer()[B
					astore_2;
				L1:	aload_2;
					sconst_0;
					getfield_b_this 17;		// byte HospitalCard/UserApplet.pinChangedFlag
					bastore;
					aload_1;
					sconst_0;
					sconst_1;
					invokevirtual 79;		// javacard/framework/APDU.setOutgoingAndSend(SS)V
					return;
		}

		.method private parseIssueCardInput([B[S)V {
			.stack 6;
			.locals 14;

				L0:	sconst_5;
					sstore_3;
				L1:	sconst_0;
					sstore 4;
				L2:	sload_3;
					sstore 5;
				L3:	sconst_0;
					sstore 6;
				L4:	sload 6;
					bspush 16;
					if_scmpge L8;
				L5:	aload_1;
					sload 5;
					sload 6;
					sadd;
					baload;
					ifeq L7;
				L6:	sconst_1;
					sstore 4;
					goto L8;
				L7:	sinc 6 1;
					goto L4;
				L8:	sload 4;
					ifeq L10;
				L9:	aload_1;
					sload 5;
					getfield_a_this 0;		// reference HospitalCard/UserApplet.cardID
					sconst_0;
					bspush 16;
					invokestatic 34;		// javacard/framework/Util.arrayCopyNonAtomic([BS[BSS)S
					pop;
					sinc 3 16;
					goto L11;
				L10:	getfield_a_this 24;		// reference HospitalCard/UserApplet.randomData
					getfield_a_this 0;		// reference HospitalCard/UserApplet.cardID
					sconst_0;
					bspush 16;
					invokevirtual 107;		// javacard/security/RandomData.generateData([BSS)V
				L11:	aload_1;
					sload_3;
					invokestatic 45;		// javacard/framework/Util.getShort([BS)S
					sstore 6;
				L12:	sinc 3 2;
					sload 6;
					ifle L14;
				L13:	sload 6;
					sspush 256;
					if_scmple L15;
				L14:	sspush 28480;
					invokestatic 44;		// javacard/framework/ISOException.throwIt(S)V
				L15:	sload_3;
					sstore 7;
				L16:	sload_3;
					sload 6;
					sadd;
					sstore_3;
					sload_3;
					sstore 8;
				L17:	bspush 6;
					sstore 9;
				L18:	sload_3;
					sload 9;
					sadd;
					sstore_3;
					sload_3;
					sstore 10;
				L19:	bspush 6;
					sstore 11;
				L20:	sload_3;
					sload 11;
					sadd;
					sstore_3;
					iconst_0;
					istore 12;
				L21:	aload_1;
					sconst_4;
					baload;
					sspush 255;
					sand;
					sstore 14;
				L22:	sload 4;
					ifeq L24;
				L23:	bspush 16;
					goto L25;
				L24:	sconst_0;
				L25:	sstore 15;
				L26:	sload 15;
					sconst_2;
					sadd;
					sload 6;
					sadd;
					sload 9;
					sadd;
					sload 11;
					sadd;
					sstore 16;
				L27:	sload 14;
					s2i;
					sload 16;
					s2i;
					iconst_4;
					iadd;
					icmp;
					iflt L29;
				L28:	aload_1;
					sload_3;
					invokestatic 105;		// HospitalCard/DataHelper.getInt([BS)I
					istore 12;
				L29:	aload_2;
					sconst_0;
					sload 4;
					ifeq L31;
				L30:	sconst_1;
					goto L32;
				L31:	sconst_0;
				L32:	sastore;
					aload_2;
					sconst_1;
					sload 7;
					sastore;
					aload_2;
					sconst_2;
					sload 6;
					sastore;
					aload_2;
					sconst_3;
					sload 8;
					sastore;
					aload_2;
					sconst_4;
					sload 10;
					sastore;
					aload_2;
					sconst_5;
					iload 12;
					bipush 16;
					iushr;
					i2s;
					sastore;
					aload_2;
					bspush 6;
					iload 12;
					iipush 65535;
					iand;
					i2s;
					sastore;
					return;
		}

		.method private generateAndInitializeKeys()V {
			.stack 4;
			.locals 1;

				L0:	getfield_a_this 24;		// reference HospitalCard/UserApplet.randomData
					getfield_a_this 9;		// reference HospitalCard/UserApplet.mkUser
					sconst_0;
					bspush 16;
					invokevirtual 107;		// javacard/security/RandomData.generateData([BSS)V
				L1:	getfield_a_this 25;		// reference HospitalCard/UserApplet.rsaKeyPair
					invokestatic 98;		// HospitalCard/RSAHelper.generateKeyPair(Ljavacard/security/KeyPair;)Z
					ifne L3;
				L2:	sspush 28417;
					invokestatic 44;		// javacard/framework/ISOException.throwIt(S)V
				L3:	aload_0;
					getfield_a_this 25;		// reference HospitalCard/UserApplet.rsaKeyPair
					invokevirtual 58;		// javacard/security/KeyPair.getPrivate()Ljavacard/security/PrivateKey;
					checkcast 0 53;		// T_CLASSORINTERFACE javacard/security/RSAPrivateKey
					putfield_a 27;		// reference HospitalCard/UserApplet.skUser
					aload_0;
					getfield_a_this 25;		// reference HospitalCard/UserApplet.rsaKeyPair
					invokevirtual 100;		// javacard/security/KeyPair.getPublic()Ljavacard/security/PublicKey;
					checkcast 0 55;		// T_CLASSORINTERFACE javacard/security/RSAPublicKey
					putfield_a 28;		// reference HospitalCard/UserApplet.pkUser
					getfield_a_this 27;		// reference HospitalCard/UserApplet.skUser
					ifnull L7;
				L4:	getfield_a_this 28;		// reference HospitalCard/UserApplet.pkUser
					ifnull L7;
				L5:	getfield_a_this 27;		// reference HospitalCard/UserApplet.skUser
					invokeinterface 1 53 3;		// javacard/security/RSAPrivateKey
					ifeq L7;
				L6:	getfield_a_this 28;		// reference HospitalCard/UserApplet.pkUser
					invokeinterface 1 55 3;		// javacard/security/RSAPublicKey
					ifne L8;
				L7:	sspush 28417;
					invokestatic 44;		// javacard/framework/ISOException.throwIt(S)V
				L8:	goto L11;
				L9:	astore_1;
				L10:	sspush 28432;
					aload_1;
					invokevirtual 43;		// javacard/security/CryptoException.getReason()S
					bspush 15;
					sand;
					sor;
					invokestatic 44;		// javacard/framework/ISOException.throwIt(S)V
				L11:	return;
			.exceptionTable {
				// start_block end_block handler_block catch_type_index
				L1 L8 L9 42;
			}
		}

		.method private setupPINsAndEncryptMK([BSS)V {
			.stack 14;
			.locals 0;

				L0:	getfield_a_this 21;		// reference HospitalCard/UserApplet.sha256
					aload_1;
					sload_2;
					bspush 6;
					getfield_a_this 1;		// reference HospitalCard/UserApplet.hashPinUser
					sconst_0;
					invokestatic 96;		// HospitalCard/PINHelper.safeHash(Ljavacard/security/MessageDigest;[BSS[BS)V
					getfield_a_this 21;		// reference HospitalCard/UserApplet.sha256
					aload_1;
					sload_3;
					bspush 6;
					getfield_a_this 2;		// reference HospitalCard/UserApplet.hashPinAdminReset
					sconst_0;
					invokestatic 96;		// HospitalCard/PINHelper.safeHash(Ljavacard/security/MessageDigest;[BSS[BS)V
					aload_1;
					sload_2;
					bspush 6;
					getfield_a_this 0;		// reference HospitalCard/UserApplet.cardID
					sconst_0;
					bspush 16;
					sspush 1000;
					getfield_a_this 9;		// reference HospitalCard/UserApplet.mkUser
					getfield_a_this 3;		// reference HospitalCard/UserApplet.encUser
					getfield_a_this 22;		// reference HospitalCard/UserApplet.aesCipher
					getfield_a_this 23;		// reference HospitalCard/UserApplet.aesKey
					getfield_a_this 21;		// reference HospitalCard/UserApplet.sha256
					getfield_a_this 12;		// reference HospitalCard/UserApplet.tempDecryptBuffer
					sconst_0;
					invokestatic 102;		// HospitalCard/CryptoHelper.wrapMasterKeyWithPIN([BSS[BSSS[B[BLjavacardx/crypto/Cipher;Ljavacard/security/AESKey;Ljavacard/security/MessageDigest;[BS)V
					aload_1;
					sload_3;
					bspush 6;
					getfield_a_this 0;		// reference HospitalCard/UserApplet.cardID
					sconst_0;
					bspush 16;
					sspush 1000;
					getfield_a_this 9;		// reference HospitalCard/UserApplet.mkUser
					getfield_a_this 4;		// reference HospitalCard/UserApplet.encAdmin
					getfield_a_this 22;		// reference HospitalCard/UserApplet.aesCipher
					getfield_a_this 23;		// reference HospitalCard/UserApplet.aesKey
					getfield_a_this 21;		// reference HospitalCard/UserApplet.sha256
					getfield_a_this 12;		// reference HospitalCard/UserApplet.tempDecryptBuffer
					sconst_0;
					invokestatic 102;		// HospitalCard/CryptoHelper.wrapMasterKeyWithPIN([BSS[BSSS[B[BLjavacardx/crypto/Cipher;Ljavacard/security/AESKey;Ljavacard/security/MessageDigest;[BS)V
					return;
		}

		.method private encryptAndStorePatientData([BSS)V {
			.stack 7;
			.locals 2;

				L0:	getfield_a_this 23;		// reference HospitalCard/UserApplet.aesKey
					getfield_a_this 9;		// reference HospitalCard/UserApplet.mkUser
					sconst_0;
					invokeinterface 3 37 4;		// javacard/security/AESKey
					getfield_a_this 22;		// reference HospitalCard/UserApplet.aesCipher
					getfield_a_this 23;		// reference HospitalCard/UserApplet.aesKey
					sconst_2;
					invokevirtual 38;		// javacardx/crypto/Cipher.init(Ljavacard/security/Key;B)V
					sload_3;
					s2i;
					bipush 15;
					iadd;
					bipush 16;
					idiv;
					bipush 16;
					imul;
					i2s;
					sstore 4;
				L1:	sload 4;
					sconst_2;
					invokestatic 39;		// javacard/framework/JCSystem.makeTransientByteArray(SB)[B
					astore 5;
				L2:	aload_1;
					sload_2;
					aload 5;
					sconst_0;
					sload_3;
					invokestatic 34;		// javacard/framework/Util.arrayCopyNonAtomic([BS[BSS)S
					pop;
					aload_0;
					getfield_a_this 22;		// reference HospitalCard/UserApplet.aesCipher
					aload 5;
					sconst_0;
					sload 4;
					getfield_a_this 5;		// reference HospitalCard/UserApplet.encPatient
					sconst_0;
					invokevirtual 40;		// javacardx/crypto/Cipher.doFinal([BSS[BS)S
					putfield_s 18;		// short HospitalCard/UserApplet.encPatientLength
				L3:	goto L6;
				L4:	astore 4;
				L5:	sspush 28420;
					invokestatic 44;		// javacard/framework/ISOException.throwIt(S)V
				L6:	return;
			.exceptionTable {
				// start_block end_block handler_block catch_type_index
				L0 L3 L4 42;
			}
		}

		.method private encryptAndStoreBalance(I)V {
			.stack 6;
			.locals 1;

				L0:	bspush 16;
					sconst_2;
					invokestatic 39;		// javacard/framework/JCSystem.makeTransientByteArray(SB)[B
					astore_3;
				L1:	aload_3;
					sconst_0;
					bspush 16;
					sconst_0;
					invokestatic 33;		// javacard/framework/Util.arrayFillNonAtomic([BSSB)S
					pop;
					aload_3;
					sconst_0;
					iload_1;
					invokestatic 47;		// HospitalCard/DataHelper.setInt([BSI)V
					getfield_a_this 23;		// reference HospitalCard/UserApplet.aesKey
					getfield_a_this 9;		// reference HospitalCard/UserApplet.mkUser
					sconst_0;
					invokeinterface 3 37 4;		// javacard/security/AESKey
					getfield_a_this 22;		// reference HospitalCard/UserApplet.aesCipher
					getfield_a_this 23;		// reference HospitalCard/UserApplet.aesKey
					sconst_2;
					invokevirtual 38;		// javacardx/crypto/Cipher.init(Ljavacard/security/Key;B)V
					getfield_a_this 22;		// reference HospitalCard/UserApplet.aesCipher
					aload_3;
					sconst_0;
					bspush 16;
					getfield_a_this 7;		// reference HospitalCard/UserApplet.encBalance
					sconst_0;
					invokevirtual 40;		// javacardx/crypto/Cipher.doFinal([BSS[BS)S
					pop;
				L2:	goto L5;
				L3:	astore_3;
				L4:	sspush 28420;
					invokestatic 44;		// javacard/framework/ISOException.throwIt(S)V
				L5:	return;
			.exceptionTable {
				// start_block end_block handler_block catch_type_index
				L0 L2 L3 42;
			}
		}

		.method private buildIssueCardResponse([B)S {
			.stack 4;
			.locals 5;

				L0:	sconst_0;
					sstore_2;
				L1:	aload_1;
					sload_2;
					sinc 2 1;
					sconst_0;
					bastore;
				L2:	getfield_a_this 28;		// reference HospitalCard/UserApplet.pkUser
					aload_1;
					sload_2;
					invokestatic 103;		// HospitalCard/RSAHelper.getPublicKeyBytes(Ljavacard/security/RSAPublicKey;[BS)S
					sstore_3;
				L3:	sload_3;
					ifle L5;
				L4:	sload_3;
					sspush 200;
					if_scmple L6;
				L5:	sspush 28418;
					invokestatic 44;		// javacard/framework/ISOException.throwIt(S)V
				L6:	sload_2;
					sload_3;
					sadd;
					sstore_2;
				L7:	goto L13;
				L8:	astore_3;
				L9:	sspush 28418;
					invokestatic 44;		// javacard/framework/ISOException.throwIt(S)V
				L10:	goto L13;
				L11:	astore_3;
				L12:	sspush 28464;
					invokestatic 44;		// javacard/framework/ISOException.throwIt(S)V
				L13:	sspush 260;
					sstore_3;
				L14:	sspush 256;
					sload_2;
					ssub;
					sstore 4;
				L15:	sload 4;
					sload_3;
					if_scmple L21;
				L16:	getfield_a_this 27;		// reference HospitalCard/UserApplet.skUser
					aload_1;
					sload_2;
					sconst_2;
					sadd;
					invokeinterface 3 53 5;		// javacard/security/RSAPrivateKey
					sstore 5;
				L17:	aload_1;
					sload_2;
					sload 5;
					invokestatic 48;		// javacard/framework/Util.setShort([BSS)S
					pop;
					sload_2;
					sconst_2;
					sload 5;
					sadd;
					sadd;
					sstore_2;
					getfield_a_this 27;		// reference HospitalCard/UserApplet.skUser
					aload_1;
					sload_2;
					sconst_2;
					sadd;
					invokeinterface 3 53 4;		// javacard/security/RSAPrivateKey
					sstore 6;
				L18:	aload_1;
					sload_2;
					sload 6;
					invokestatic 48;		// javacard/framework/Util.setShort([BSS)S
					pop;
					sload_2;
					sconst_2;
					sload 6;
					sadd;
					sadd;
					sstore_2;
				L19:	goto L21;
				L20:	astore 5;
				L21:	sload_2;
					sreturn;
			.exceptionTable {
				// start_block end_block handler_block catch_type_index
				L2 L7 L8 42;
				L2 L7 L11 80;
				L16 L19 L20 42;
			}
		}

		.method private validateAndVerifyPIN([BSS)V {
			.stack 6;
			.locals 1;

				L0:	getfield_a_this 10;		// reference HospitalCard/UserApplet.tempHashBuffer
					sconst_0;
					bspush 20;
					sconst_0;
					invokestatic 33;		// javacard/framework/Util.arrayFillNonAtomic([BSSB)S
					pop;
				L1:	getfield_a_this 21;		// reference HospitalCard/UserApplet.sha256
					invokevirtual 30;		// javacard/security/MessageDigest.reset()V
					getfield_a_this 21;		// reference HospitalCard/UserApplet.sha256
					aload_1;
					sload_2;
					sload_3;
					getfield_a_this 10;		// reference HospitalCard/UserApplet.tempHashBuffer
					sconst_0;
					invokevirtual 32;		// javacard/security/MessageDigest.doFinal([BSS[BS)S
					pop;
				L2:	goto L11;
				L3:	astore 4;
				L4:	sspush 28417;
					invokestatic 44;		// javacard/framework/ISOException.throwIt(S)V
				L5:	goto L11;
				L6:	astore 4;
				L7:	sspush 28579;
					invokestatic 44;		// javacard/framework/ISOException.throwIt(S)V
				L8:	goto L11;
				L9:	astore 4;
				L10:	sspush 28580;
					invokestatic 44;		// javacard/framework/ISOException.throwIt(S)V
				L11:	getfield_a_this 10;		// reference HospitalCard/UserApplet.tempHashBuffer
					sconst_0;
					getfield_a_this 1;		// reference HospitalCard/UserApplet.hashPinUser
					sconst_0;
					bspush 20;
					invokestatic 51;		// javacard/framework/Util.arrayCompare([BS[BSS)B
					ifeq L15;
				L12:	aload_0;
					dup;
					getfield_b 15;		// byte HospitalCard/UserApplet.pinRetryCounter
					sconst_1;
					ssub;
					s2b;
					putfield_b 15;		// byte HospitalCard/UserApplet.pinRetryCounter
					getfield_b_this 15;		// byte HospitalCard/UserApplet.pinRetryCounter
					ifne L14;
				L13:	aload_0;
					sconst_1;
					putfield_b 16;		// byte HospitalCard/UserApplet.blockedFlag
				L14:	sspush 25536;
					getfield_b_this 15;		// byte HospitalCard/UserApplet.pinRetryCounter
					sor;
					invokestatic 44;		// javacard/framework/ISOException.throwIt(S)V
				L15:	aload_0;
					sconst_5;
					putfield_b 15;		// byte HospitalCard/UserApplet.pinRetryCounter
					return;
			.exceptionTable {
				// start_block end_block handler_block catch_type_index
				L1 L2 L3 42;
				L1 L2 L6 89;
				L1 L2 L9 36;
			}
		}

		.method private decryptDataAndBuildResponse([BSSLjavacard/framework/APDU;)S {
			.stack 14;
			.locals 6;

			.descriptor	Ljavacard/framework/APDU;	2.10;

				L0:	getfield_a_this 11;		// reference HospitalCard/UserApplet.tempPinBuffer
					sconst_0;
					bspush 6;
					sconst_0;
					invokestatic 33;		// javacard/framework/Util.arrayFillNonAtomic([BSSB)S
					pop;
					aload_1;
					sload_2;
					getfield_a_this 11;		// reference HospitalCard/UserApplet.tempPinBuffer
					sconst_0;
					sload_3;
					invokestatic 34;		// javacard/framework/Util.arrayCopyNonAtomic([BS[BSS)S
					pop;
				L1:	getfield_a_this 9;		// reference HospitalCard/UserApplet.mkUser
					sconst_0;
					bspush 32;
					sconst_0;
					invokestatic 33;		// javacard/framework/Util.arrayFillNonAtomic([BSSB)S
					pop;
				L2:	goto L5;
				L3:	astore 5;
				L4:	sspush 28581;
					invokestatic 44;		// javacard/framework/ISOException.throwIt(S)V
				L5:	sconst_0;
					sstore 5;
				L6:	getfield_a_this 11;		// reference HospitalCard/UserApplet.tempPinBuffer
					sconst_0;
					sload_3;
					getfield_a_this 0;		// reference HospitalCard/UserApplet.cardID
					sconst_0;
					bspush 16;
					sspush 1000;
					getfield_a_this 3;		// reference HospitalCard/UserApplet.encUser
					getfield_a_this 9;		// reference HospitalCard/UserApplet.mkUser
					getfield_a_this 22;		// reference HospitalCard/UserApplet.aesCipher
					getfield_a_this 23;		// reference HospitalCard/UserApplet.aesKey
					getfield_a_this 21;		// reference HospitalCard/UserApplet.sha256
					getfield_a_this 12;		// reference HospitalCard/UserApplet.tempDecryptBuffer
					sconst_0;
					invokestatic 97;		// HospitalCard/CryptoHelper.unwrapMasterKeyWithPIN([BSS[BSSS[B[BLjavacardx/crypto/Cipher;Ljavacard/security/AESKey;Ljavacard/security/MessageDigest;[BS)Z
					sstore 5;
				L7:	goto L10;
				L8:	astore 6;
				L9:	sspush 28588;
					invokestatic 44;		// javacard/framework/ISOException.throwIt(S)V
				L10:	sload 5;
					ifne L12;
				L11:	getfield_a_this 9;		// reference HospitalCard/UserApplet.mkUser
					sconst_0;
					bspush 32;
					sconst_0;
					invokestatic 33;		// javacard/framework/Util.arrayFillNonAtomic([BSSB)S
					pop;
					sspush 28420;
					invokestatic 44;		// javacard/framework/ISOException.throwIt(S)V
				L12:	getfield_a_this 12;		// reference HospitalCard/UserApplet.tempDecryptBuffer
					sconst_0;
					sspush 256;
					sconst_0;
					invokestatic 33;		// javacard/framework/Util.arrayFillNonAtomic([BSSB)S
					pop;
					sconst_0;
					sstore 6;
				L13:	getfield_a_this 23;		// reference HospitalCard/UserApplet.aesKey
					getfield_a_this 9;		// reference HospitalCard/UserApplet.mkUser
					sconst_0;
					invokeinterface 3 37 4;		// javacard/security/AESKey
					getfield_a_this 22;		// reference HospitalCard/UserApplet.aesCipher
					getfield_a_this 23;		// reference HospitalCard/UserApplet.aesKey
					sconst_1;
					invokevirtual 38;		// javacardx/crypto/Cipher.init(Ljavacard/security/Key;B)V
					getfield_a_this 22;		// reference HospitalCard/UserApplet.aesCipher
					getfield_a_this 5;		// reference HospitalCard/UserApplet.encPatient
					sconst_0;
					getfield_s_this 18;		// short HospitalCard/UserApplet.encPatientLength
					getfield_a_this 12;		// reference HospitalCard/UserApplet.tempDecryptBuffer
					sconst_0;
					invokevirtual 40;		// javacardx/crypto/Cipher.doFinal([BSS[BS)S
					sstore 6;
				L14:	sload 6;
					ifle L17;
				L15:	getfield_a_this 12;		// reference HospitalCard/UserApplet.tempDecryptBuffer
					sload 6;
					sconst_1;
					ssub;
					baload;
					ifne L17;
				L16:	sinc 6 -1;
					goto L14;
				L17:	goto L23;
				L18:	astore 7;
				L19:	sspush 28421;
					invokestatic 44;		// javacard/framework/ISOException.throwIt(S)V
				L20:	goto L23;
				L21:	astore 7;
				L22:	sspush 28589;
					invokestatic 44;		// javacard/framework/ISOException.throwIt(S)V
				L23:	getfield_a_this 13;		// reference HospitalCard/UserApplet.tempBalanceBuffer
					sconst_0;
					bspush 16;
					sconst_0;
					invokestatic 33;		// javacard/framework/Util.arrayFillNonAtomic([BSSB)S
					pop;
					iconst_0;
					istore 7;
				L24:	getfield_a_this 23;		// reference HospitalCard/UserApplet.aesKey
					getfield_a_this 9;		// reference HospitalCard/UserApplet.mkUser
					sconst_0;
					invokeinterface 3 37 4;		// javacard/security/AESKey
					getfield_a_this 22;		// reference HospitalCard/UserApplet.aesCipher
					getfield_a_this 23;		// reference HospitalCard/UserApplet.aesKey
					sconst_1;
					invokevirtual 38;		// javacardx/crypto/Cipher.init(Ljavacard/security/Key;B)V
					getfield_a_this 22;		// reference HospitalCard/UserApplet.aesCipher
					getfield_a_this 7;		// reference HospitalCard/UserApplet.encBalance
					sconst_0;
					bspush 16;
					getfield_a_this 13;		// reference HospitalCard/UserApplet.tempBalanceBuffer
					sconst_0;
					invokevirtual 40;		// javacardx/crypto/Cipher.doFinal([BSS[BS)S
					pop;
					getfield_a_this 13;		// reference HospitalCard/UserApplet.tempBalanceBuffer
					sconst_0;
					invokestatic 105;		// HospitalCard/DataHelper.getInt([BS)I
					istore 7;
				L25:	goto L31;
				L26:	astore 9;
				L27:	sspush 28422;
					invokestatic 44;		// javacard/framework/ISOException.throwIt(S)V
				L28:	goto L31;
				L29:	astore 9;
				L30:	sspush 28590;
					invokestatic 44;		// javacard/framework/ISOException.throwIt(S)V
				L31:	sconst_0;
					sstore 9;
				L32:	aload_1;
					sload 9;
					sinc 9 1;
					sconst_0;
					bastore;
					aload_1;
					sload 9;
					sload 6;
					invokestatic 48;		// javacard/framework/Util.setShort([BSS)S
					pop;
					sinc 9 2;
					getfield_a_this 12;		// reference HospitalCard/UserApplet.tempDecryptBuffer
					sconst_0;
					aload_1;
					sload 9;
					sload 6;
					invokestatic 34;		// javacard/framework/Util.arrayCopyNonAtomic([BS[BSS)S
					pop;
					sload 9;
					sload 6;
					sadd;
					sstore 9;
					aload_1;
					sload 9;
					iload 7;
					invokestatic 47;		// HospitalCard/DataHelper.setInt([BSI)V
					sinc 9 4;
				L33:	goto L36;
				L34:	astore 10;
				L35:	sspush 28584;
					invokestatic 44;		// javacard/framework/ISOException.throwIt(S)V
				L36:	sload 9;
					sreturn;
			.exceptionTable {
				// start_block end_block handler_block catch_type_index
				L1 L2 L3 36;
				L6 L7 L8 36;
				L13 L17 L18 42;
				L13 L17 L21 36;
				L24 L25 L26 42;
				L24 L25 L29 36;
				L32 L33 L34 36;
			}
		}

		.method private validatePINChange([BSSSS[B)V {
			.stack 6;
			.locals 1;

				L0:	getfield_a_this 21;		// reference HospitalCard/UserApplet.sha256
					invokevirtual 30;		// javacard/security/MessageDigest.reset()V
					getfield_a_this 21;		// reference HospitalCard/UserApplet.sha256
					aload_1;
					sload_2;
					sload_3;
					getfield_a_this 12;		// reference HospitalCard/UserApplet.tempDecryptBuffer
					sconst_0;
					invokevirtual 32;		// javacard/security/MessageDigest.doFinal([BSS[BS)S
					pop;
				L1:	goto L4;
				L2:	astore 7;
				L3:	sspush 28417;
					invokestatic 44;		// javacard/framework/ISOException.throwIt(S)V
				L4:	getfield_a_this 12;		// reference HospitalCard/UserApplet.tempDecryptBuffer
					sconst_0;
					getfield_a_this 1;		// reference HospitalCard/UserApplet.hashPinUser
					sconst_0;
					bspush 20;
					invokestatic 51;		// javacard/framework/Util.arrayCompare([BS[BSS)B
					ifeq L8;
				L5:	aload_0;
					dup;
					getfield_b 15;		// byte HospitalCard/UserApplet.pinRetryCounter
					sconst_1;
					ssub;
					s2b;
					putfield_b 15;		// byte HospitalCard/UserApplet.pinRetryCounter
					getfield_b_this 15;		// byte HospitalCard/UserApplet.pinRetryCounter
					ifne L7;
				L6:	aload_0;
					sconst_1;
					putfield_b 16;		// byte HospitalCard/UserApplet.blockedFlag
				L7:	sspush 25536;
					getfield_b_this 15;		// byte HospitalCard/UserApplet.pinRetryCounter
					sor;
					invokestatic 44;		// javacard/framework/ISOException.throwIt(S)V
				L8:	getfield_a_this 21;		// reference HospitalCard/UserApplet.sha256
					invokevirtual 30;		// javacard/security/MessageDigest.reset()V
					getfield_a_this 21;		// reference HospitalCard/UserApplet.sha256
					aload_1;
					sload 4;
					sload 5;
					aload 6;
					sconst_0;
					invokevirtual 32;		// javacard/security/MessageDigest.doFinal([BSS[BS)S
					pop;
				L9:	goto L12;
				L10:	astore 7;
				L11:	sspush 28417;
					invokestatic 44;		// javacard/framework/ISOException.throwIt(S)V
				L12:	aload 6;
					sconst_0;
					getfield_a_this 1;		// reference HospitalCard/UserApplet.hashPinUser
					sconst_0;
					bspush 20;
					invokestatic 51;		// javacard/framework/Util.arrayCompare([BS[BSS)B
					ifne L14;
				L13:	sspush 27264;
					invokestatic 44;		// javacard/framework/ISOException.throwIt(S)V
				L14:	return;
			.exceptionTable {
				// start_block end_block handler_block catch_type_index
				L0 L1 L2 42;
				L8 L9 L10 42;
			}
		}

		.method private reEncryptMasterKeyWithNewPIN([BSSSS[B)V {
			.stack 14;
			.locals 2;

				L0:	getfield_a_this 9;		// reference HospitalCard/UserApplet.mkUser
					sconst_0;
					bspush 32;
					sconst_0;
					invokestatic 33;		// javacard/framework/Util.arrayFillNonAtomic([BSSB)S
					pop;
					aload_1;
					sload_2;
					sload_3;
					getfield_a_this 0;		// reference HospitalCard/UserApplet.cardID
					sconst_0;
					bspush 16;
					sspush 1000;
					getfield_a_this 3;		// reference HospitalCard/UserApplet.encUser
					getfield_a_this 9;		// reference HospitalCard/UserApplet.mkUser
					getfield_a_this 22;		// reference HospitalCard/UserApplet.aesCipher
					getfield_a_this 23;		// reference HospitalCard/UserApplet.aesKey
					getfield_a_this 21;		// reference HospitalCard/UserApplet.sha256
					getfield_a_this 12;		// reference HospitalCard/UserApplet.tempDecryptBuffer
					sconst_0;
					invokestatic 97;		// HospitalCard/CryptoHelper.unwrapMasterKeyWithPIN([BSS[BSSS[B[BLjavacardx/crypto/Cipher;Ljavacard/security/AESKey;Ljavacard/security/MessageDigest;[BS)Z
					sstore 7;
				L1:	sload 7;
					ifne L3;
				L2:	getfield_a_this 9;		// reference HospitalCard/UserApplet.mkUser
					sconst_0;
					bspush 32;
					sconst_0;
					invokestatic 33;		// javacard/framework/Util.arrayFillNonAtomic([BSSB)S
					pop;
					sspush 28420;
					invokestatic 44;		// javacard/framework/ISOException.throwIt(S)V
				L3:	aload_0;
					invokespecial 93;		// HospitalCard/UserApplet.isMasterKeyValid()Z
					ifne L5;
				L4:	getfield_a_this 9;		// reference HospitalCard/UserApplet.mkUser
					sconst_0;
					bspush 32;
					sconst_0;
					invokestatic 33;		// javacard/framework/Util.arrayFillNonAtomic([BSSB)S
					pop;
					sspush 28420;
					invokestatic 44;		// javacard/framework/ISOException.throwIt(S)V
				L5:	aload_1;
					sload 4;
					sload 5;
					getfield_a_this 0;		// reference HospitalCard/UserApplet.cardID
					sconst_0;
					bspush 16;
					sspush 1000;
					getfield_a_this 9;		// reference HospitalCard/UserApplet.mkUser
					getfield_a_this 3;		// reference HospitalCard/UserApplet.encUser
					getfield_a_this 22;		// reference HospitalCard/UserApplet.aesCipher
					getfield_a_this 23;		// reference HospitalCard/UserApplet.aesKey
					getfield_a_this 21;		// reference HospitalCard/UserApplet.sha256
					getfield_a_this 12;		// reference HospitalCard/UserApplet.tempDecryptBuffer
					sconst_0;
					invokestatic 102;		// HospitalCard/CryptoHelper.wrapMasterKeyWithPIN([BSS[BSSS[B[BLjavacardx/crypto/Cipher;Ljavacard/security/AESKey;Ljavacard/security/MessageDigest;[BS)V
				L6:	goto L9;
				L7:	astore 8;
				L8:	getfield_a_this 9;		// reference HospitalCard/UserApplet.mkUser
					sconst_0;
					bspush 32;
					sconst_0;
					invokestatic 33;		// javacard/framework/Util.arrayFillNonAtomic([BSSB)S
					pop;
					sspush 28420;
					invokestatic 44;		// javacard/framework/ISOException.throwIt(S)V
				L9:	aload 6;
					sconst_0;
					getfield_a_this 1;		// reference HospitalCard/UserApplet.hashPinUser
					sconst_0;
					bspush 20;
					invokestatic 34;		// javacard/framework/Util.arrayCopyNonAtomic([BS[BSS)S
					pop;
					aload_0;
					sconst_5;
					putfield_b 15;		// byte HospitalCard/UserApplet.pinRetryCounter
					aload_0;
					sconst_1;
					putfield_b 17;		// byte HospitalCard/UserApplet.pinChangedFlag
					getfield_a_this 9;		// reference HospitalCard/UserApplet.mkUser
					sconst_0;
					bspush 32;
					sconst_0;
					invokestatic 33;		// javacard/framework/Util.arrayFillNonAtomic([BSSB)S
					pop;
					return;
			.exceptionTable {
				// start_block end_block handler_block catch_type_index
				L5 L6 L7 36;
			}
		}

		.method private setPhoto(Ljavacard/framework/APDU;)V {
			.stack 7;
			.locals 8;

			.descriptor	Ljavacard/framework/APDU;	2.10;

				L0:	getfield_b_this 14;		// byte HospitalCard/UserApplet.initialized
					sconst_1;
					if_scmpeq L2;
				L1:	sspush 27013;
					invokestatic 44;		// javacard/framework/ISOException.throwIt(S)V
				L2:	aload_0;
					invokespecial 93;		// HospitalCard/UserApplet.isMasterKeyValid()Z
					ifne L4;
				L3:	sspush 27010;
					invokestatic 44;		// javacard/framework/ISOException.throwIt(S)V
				L4:	aload_1;
					invokevirtual 64;		// javacard/framework/APDU.getBuffer()[B
					astore_2;
				L5:	sconst_5;
					sstore_3;
				L6:	aload_2;
					sload_3;
					invokestatic 45;		// javacard/framework/Util.getShort([BS)S
					sstore 4;
				L7:	sinc 3 2;
					aload_2;
					sload_3;
					invokestatic 45;		// javacard/framework/Util.getShort([BS)S
					sstore 5;
				L8:	sinc 3 2;
					aload_2;
					sconst_4;
					baload;
					sspush 255;
					sand;
					sstore 6;
				L9:	sload 6;
					sconst_4;
					ssub;
					sstore 7;
				L10:	sload 7;
					ifle L12;
				L11:	sload 7;
					sspush 200;
					if_scmple L13;
				L12:	sspush 26368;
					invokestatic 44;		// javacard/framework/ISOException.throwIt(S)V
				L13:	sload 4;
					ifne L15;
				L14:	aload_0;
					sconst_0;
					putfield_s 19;		// short HospitalCard/UserApplet.encPhotoLength
					getfield_a_this 6;		// reference HospitalCard/UserApplet.encPhoto
					sconst_0;
					sspush 20480;
					sconst_0;
					invokestatic 33;		// javacard/framework/Util.arrayFillNonAtomic([BSSB)S
					pop;
				L15:	sload 4;
					sspush 200;
					smul;
					sstore 8;
				L16:	sload 8;
					sload 7;
					sadd;
					sspush 20480;
					if_scmple L18;
				L17:	sspush 27264;
					invokestatic 44;		// javacard/framework/ISOException.throwIt(S)V
				L18:	aload_2;
					sload_3;
					getfield_a_this 6;		// reference HospitalCard/UserApplet.encPhoto
					sload 8;
					sload 7;
					invokestatic 34;		// javacard/framework/Util.arrayCopyNonAtomic([BS[BSS)S
					pop;
					sload 8;
					sload 7;
					sadd;
					getfield_s_this 19;		// short HospitalCard/UserApplet.encPhotoLength
					if_scmple L20;
				L19:	aload_0;
					sload 8;
					sload 7;
					sadd;
					putfield_s 19;		// short HospitalCard/UserApplet.encPhotoLength
				L20:	sload 4;
					sload 5;
					sconst_1;
					ssub;
					if_scmpne L25;
				L21:	getfield_s_this 19;		// short HospitalCard/UserApplet.encPhotoLength
					s2i;
					bipush 15;
					iadd;
					bipush 16;
					idiv;
					bipush 16;
					imul;
					i2s;
					sstore 9;
				L22:	sload 9;
					getfield_s_this 19;		// short HospitalCard/UserApplet.encPhotoLength
					if_scmple L24;
				L23:	getfield_a_this 6;		// reference HospitalCard/UserApplet.encPhoto
					getfield_s_this 19;		// short HospitalCard/UserApplet.encPhotoLength
					sload 9;
					getfield_s_this 19;		// short HospitalCard/UserApplet.encPhotoLength
					ssub;
					sconst_0;
					invokestatic 33;		// javacard/framework/Util.arrayFillNonAtomic([BSSB)S
					pop;
				L24:	getfield_a_this 23;		// reference HospitalCard/UserApplet.aesKey
					getfield_a_this 9;		// reference HospitalCard/UserApplet.mkUser
					sconst_0;
					invokeinterface 3 37 4;		// javacard/security/AESKey
					getfield_a_this 22;		// reference HospitalCard/UserApplet.aesCipher
					getfield_a_this 23;		// reference HospitalCard/UserApplet.aesKey
					sconst_2;
					invokevirtual 38;		// javacardx/crypto/Cipher.init(Ljavacard/security/Key;B)V
					aload_0;
					getfield_a_this 22;		// reference HospitalCard/UserApplet.aesCipher
					getfield_a_this 6;		// reference HospitalCard/UserApplet.encPhoto
					sconst_0;
					sload 9;
					getfield_a_this 6;		// reference HospitalCard/UserApplet.encPhoto
					sconst_0;
					invokevirtual 40;		// javacardx/crypto/Cipher.doFinal([BSS[BS)S
					putfield_s 19;		// short HospitalCard/UserApplet.encPhotoLength
				L25:	aload_2;
					sconst_0;
					sconst_0;
					bastore;
					aload_1;
					sconst_0;
					sconst_1;
					invokevirtual 79;		// javacard/framework/APDU.setOutgoingAndSend(SS)V
				L26:	goto L32;
				L27:	astore 4;
				L28:	sspush 28416;
					aload 4;
					invokevirtual 43;		// javacard/security/CryptoException.getReason()S
					sor;
					invokestatic 44;		// javacard/framework/ISOException.throwIt(S)V
				L29:	goto L32;
				L30:	astore 4;
				L31:	sspush 28416;
					invokestatic 44;		// javacard/framework/ISOException.throwIt(S)V
				L32:	return;
			.exceptionTable {
				// start_block end_block handler_block catch_type_index
				L6 L26 L27 42;
				L6 L26 L30 36;
			}
		}

		.method private getPhoto(Ljavacard/framework/APDU;)V {
			.stack 7;
			.locals 8;

			.descriptor	Ljavacard/framework/APDU;	2.10;

				L0:	getfield_b_this 14;		// byte HospitalCard/UserApplet.initialized
					sconst_1;
					if_scmpeq L2;
				L1:	sspush 27013;
					invokestatic 44;		// javacard/framework/ISOException.throwIt(S)V
				L2:	aload_0;
					invokespecial 93;		// HospitalCard/UserApplet.isMasterKeyValid()Z
					ifne L4;
				L3:	sspush 27010;
					invokestatic 44;		// javacard/framework/ISOException.throwIt(S)V
				L4:	aload_1;
					invokevirtual 64;		// javacard/framework/APDU.getBuffer()[B
					astore_2;
				L5:	aload_2;
					sconst_2;
					baload;
					sstore_3;
				L6:	getfield_s_this 19;		// short HospitalCard/UserApplet.encPhotoLength
					ifne L9;
				L7:	aload_2;
					sconst_0;
					sconst_0;
					invokestatic 48;		// javacard/framework/Util.setShort([BSS)S
					pop;
					aload_1;
					sconst_0;
					sconst_2;
					invokevirtual 79;		// javacard/framework/APDU.setOutgoingAndSend(SS)V
				L8:	return;
				L9:	getfield_a_this 23;		// reference HospitalCard/UserApplet.aesKey
					getfield_a_this 9;		// reference HospitalCard/UserApplet.mkUser
					sconst_0;
					invokeinterface 3 37 4;		// javacard/security/AESKey
					getfield_a_this 22;		// reference HospitalCard/UserApplet.aesCipher
					getfield_a_this 23;		// reference HospitalCard/UserApplet.aesKey
					sconst_1;
					invokevirtual 38;		// javacardx/crypto/Cipher.init(Ljavacard/security/Key;B)V
					getfield_a_this 22;		// reference HospitalCard/UserApplet.aesCipher
					getfield_a_this 6;		// reference HospitalCard/UserApplet.encPhoto
					sconst_0;
					getfield_s_this 19;		// short HospitalCard/UserApplet.encPhotoLength
					getfield_a_this 6;		// reference HospitalCard/UserApplet.encPhoto
					sconst_0;
					invokevirtual 40;		// javacardx/crypto/Cipher.doFinal([BSS[BS)S
					sstore 4;
				L10:	sload 4;
					sstore 5;
				L11:	sload 4;
					sconst_1;
					ssub;
					sstore 6;
				L12:	sload 6;
					iflt L16;
				L13:	getfield_a_this 6;		// reference HospitalCard/UserApplet.encPhoto
					sload 6;
					baload;
					ifeq L15;
				L14:	sload 6;
					sconst_1;
					sadd;
					sstore 5;
					goto L16;
				L15:	sinc 6 -1;
					goto L12;
				L16:	sconst_0;
					sstore 6;
				L17:	sload_3;
					ifne L23;
				L18:	aload_2;
					sload 6;
					sload 5;
					invokestatic 48;		// javacard/framework/Util.setShort([BSS)S
					pop;
					sinc 6 2;
					sload 5;
					sstore 7;
				L19:	sload 7;
					sspush 250;
					if_scmple L21;
				L20:	sspush 250;
					sstore 7;
				L21:	getfield_a_this 6;		// reference HospitalCard/UserApplet.encPhoto
					sconst_0;
					aload_2;
					sload 6;
					sload 7;
					invokestatic 34;		// javacard/framework/Util.arrayCopyNonAtomic([BS[BSS)S
					pop;
					sload 6;
					sload 7;
					sadd;
					sstore 6;
				L22:	goto L32;
				L23:	sspush 250;
					sload_3;
					sconst_1;
					ssub;
					sspush 252;
					smul;
					sadd;
					sstore 7;
				L24:	sload 7;
					sload 5;
					if_scmplt L27;
				L25:	aload_1;
					sconst_0;
					sconst_0;
					invokevirtual 79;		// javacard/framework/APDU.setOutgoingAndSend(SS)V
				L26:	return;
				L27:	sload 5;
					sload 7;
					ssub;
					sstore 8;
				L28:	sload 8;
					sstore 9;
				L29:	sload 9;
					sspush 252;
					if_scmple L31;
				L30:	sspush 252;
					sstore 9;
				L31:	getfield_a_this 6;		// reference HospitalCard/UserApplet.encPhoto
					sload 7;
					aload_2;
					sload 6;
					sload 9;
					invokestatic 34;		// javacard/framework/Util.arrayCopyNonAtomic([BS[BSS)S
					pop;
					sload 6;
					sload 9;
					sadd;
					sstore 6;
				L32:	aload_1;
					sconst_0;
					sload 6;
					invokevirtual 79;		// javacard/framework/APDU.setOutgoingAndSend(SS)V
					getfield_a_this 22;		// reference HospitalCard/UserApplet.aesCipher
					getfield_a_this 23;		// reference HospitalCard/UserApplet.aesKey
					sconst_2;
					invokevirtual 38;		// javacardx/crypto/Cipher.init(Ljavacard/security/Key;B)V
					sload 5;
					s2i;
					bipush 15;
					iadd;
					bipush 16;
					idiv;
					bipush 16;
					imul;
					i2s;
					sstore 7;
				L33:	sload 7;
					sload 5;
					if_scmple L35;
				L34:	getfield_a_this 6;		// reference HospitalCard/UserApplet.encPhoto
					sload 5;
					sload 7;
					sload 5;
					ssub;
					sconst_0;
					invokestatic 33;		// javacard/framework/Util.arrayFillNonAtomic([BSSB)S
					pop;
				L35:	aload_0;
					getfield_a_this 22;		// reference HospitalCard/UserApplet.aesCipher
					getfield_a_this 6;		// reference HospitalCard/UserApplet.encPhoto
					sconst_0;
					sload 7;
					getfield_a_this 6;		// reference HospitalCard/UserApplet.encPhoto
					sconst_0;
					invokevirtual 40;		// javacardx/crypto/Cipher.doFinal([BSS[BS)S
					putfield_s 19;		// short HospitalCard/UserApplet.encPhotoLength
				L36:	goto L39;
				L37:	astore 4;
				L38:	sspush 28416;
					aload 4;
					invokevirtual 43;		// javacard/security/CryptoException.getReason()S
					sor;
					invokestatic 44;		// javacard/framework/ISOException.throwIt(S)V
				L39:	return;
			.exceptionTable {
				// start_block end_block handler_block catch_type_index
				L6 L8 L37 42;
				L9 L26 L37 42;
				L27 L36 L37 42;
			}
		}

	}

}
